Workbook

Sheet Start here
A1: Post-award control workbook — Northbridge Foundation (synthetic)
A2: Built 28 Sep 2026 from your grant list. The figures below update automatically when you edit the Grant register and Payments sheets.
A3: SYNTHETIC EXAMPLE — fictional organisation and data, for illustration only.
A5: Active grants | B5: =COUNTA('Grant register'!A2:A500) -> 19
A6: Total awarded | B6: =SUM('Grant register'!F2:F500) -> 235700
A7: Paid to date | B7: =SUMIFS(Payments!D2:D500,Payments!I2:I500,"<>") -> 152850
A8: Reports overdue | B8: =COUNTIF('Grant register'!T2:T500,"*overdue*")
A9: Reports due in the next 30 days | B9: =COUNTIF('Grant register'!T2:T500,"*due in*")
A10: Payments blocked | B10: =COUNTIF(Payments!J2:J500,"Blocked*") -> 8
A11: Value of blocked payments | B11: =SUMIF(Payments!J2:J500,"Blocked*",Payments!D2:D500) -> 58850
A12: Payments ready for approval | B12: =COUNTIF(Payments!J2:J500,"Ready*") -> 1
A13: Grants with evidence missing or partial | B13: =COUNTIF('Grant register'!S2:S500,"Missing")+COUNTIF('Grant register'!S2:S500,"Partial") -> 4
A14: Grants with a due-diligence gap | B14: =COUNTIF('Grant register'!V2:V500,"*DD*")
A15: Open grant conditions | B15: =COUNTIF('Grant register'!M2:M500,"No") -> 4
A16: Data questions for you to confirm | B16: 23
A18: Top actions (as at 28 Sep 2026)
A19: Issue | B19: Priority | C19: Grant / recipient | D19: Next action
A20: Payment on hold: bank details changed: Tranche 1 (£3,500): notes say bank details changed | B20: High | C20: CAP-10 · Eastfield Village Hall | D20: Verify the new bank details by phone on a number you already hold before paying (owner: Priya K)
A21: Payment on hold: bank details changed: Tranche 2 (£9,000): notes say bank details changed | B21: High | C21: CAP-8 · Eastfield Village Hall | D21: Verify the new bank details by phone on a number you already hold before paying (owner: Priya K)
A22: Paid before agreement recorded: £3,000 paid; no signed agreement on file | B22: High | C22: YM25/05 · St Anne's Community Choir | D22: Obtain the signed agreement and file it (owner: Tom B)
A23: Due diligence not recorded: £3,000 paid with no check recorded | B23: High | C23: HF-103 · Westside Refugee Welcome | D23: Complete the recipient check and record the date and source (owner: Sarah J)
A24: Due diligence not recorded: £3,000 paid with no check recorded | B24: High | C24: YM25/05 · St Anne's Community Choir | D24: Complete the recipient check and record the date and source (owner: Tom B)
A25: Payment late: Tranche 2 (£15,000) was due 10 Sep 2026; release conditions are met | B25: High | C25: CF-2026-002 · Lanterns Mental Health Peer Support | D25: Approve and pay, or record why it is held (owner: Sarah J)
A26: Condition overdue: Safeguarding policy to be provided within 3 months (by 20/09/2026) | B26: High | C26: YM26/02 · The Beat Box Studio CIC | D26: Chase, or record an agreed extension (owner: Tom B)
A27: Payment blocked: Tranche 2 (£3,600) was due 10 May 2026; waiting for interim report | B27: High | C27: YM25/09 · Rhythm & Roots Drumming | D27: Chase interim report; hold payment until received (owner: Tom B)
A28: Payment blocked: Tranche 2 (£6,250) was due 01 Sep 2026; waiting for interim report | B28: High | C28: YM25/03 · Northgate Music Collective | D28: Chase interim report; hold payment until received (owner: Tom B)
A29: Payment blocked: Tranche 1 (£1,500) due 30 Sep 2026; waiting for agreement | B29: High | C29: HF-102 · Mercy Street Food Bank | D29: Chase agreement; hold payment until received (owner: Sarah J)
A31: Where to look:
A32: • Needs attention — every issue found, highest priority first. Tick Done as you go.
A33: • Payments — each tranche, what releases it, and whether it is blocked or ready.
A34: • Grant register — one row per grant; status columns recalculate from the dates you enter.
A35: • Data questions — things in your export I could not be sure about. Please confirm.
A36: • How to use — keeping the workbook current.

Sheet Needs attention
A1: Needs attention — as at 28 Sep 2026 (tick Done as you clear items)
A3: Priority | B3: Grant ref | C3: Recipient | D3: Fund | E3: Issue | F3: Detail | G3: Date | H3: Days late | I3: £ | J3: Owner | K3: Next action | L3: Done? | M3: Your notes
A4: High | B4: CAP-10 | C4: Eastfield Village Hall | D4: Capital Grants | E4: Payment on hold: bank details changed | F4: Tranche 1 (£3,500): notes say bank details changed | G4: 46310 | I4: 3500 | J4: Priya K | K4: Verify the new bank details by phone on a number you already hold before paying | L4: No
A5: High | B5: CAP-8 | C5: Eastfield Village Hall | D5: Capital Grants | E5: Payment on hold: bank details changed | F5: Tranche 2 (£9,000): notes say bank details changed | G5: 46326 | I5: 9000 | J5: Priya K | K5: Verify the new bank details by phone on a number you already hold before paying | L5: No
A6: High | B6: YM25/05 | C6: St Anne's Community Choir | D6: Youth Music | E6: Paid before agreement recorded | F6: £3,000 paid; no signed agreement on file | J6: Tom B | K6: Obtain the signed agreement and file it | L6: No
A7: High | B7: HF-103 | C7: Westside Refugee Welcome | D7: Hardship Fund | E7: Due diligence not recorded | F7: £3,000 paid with no check recorded | J7: Sarah J | K7: Complete the recipient check and record the date and source | L7: No
A8: High | B8: YM25/05 | C8: St Anne's Community Choir | D8: Youth Music | E8: Due diligence not recorded | F8: £3,000 paid with no check recorded | J8: Tom B | K8: Complete the recipient check and record the date and source | L8: No
A9: High | B9: CF-2026-002 | C9: Lanterns Mental Health Peer Support | D9: Community Fund | E9: Payment late | F9: Tranche 2 (£15,000) was due 10 Sep 2026; release conditions are met | G9: 46275 | H9: 18 | I9: 15000 | J9: Sarah J | K9: Approve and pay, or record why it is held | L9: No
A10: High | B10: YM26/02 | C10: The Beat Box Studio CIC | D10: Youth Music | E10: Condition overdue | F10: Safeguarding policy to be provided within 3 months (by 20/09/2026) | G10: 46285 | H10: 8 | J10: Tom B | K10: Chase, or record an agreed extension | L10: No
A11: High | B11: YM25/09 | C11: Rhythm & Roots Drumming | D11: Youth Music | E11: Payment blocked | F11: Tranche 2 (£3,600) was due 10 May 2026; waiting for interim report | G11: 46152 | H11: 141 | I11: 3600 | J11: Tom B | K11: Chase interim report; hold payment until received | L11: No
A12: High | B12: YM25/03 | C12: Northgate Music Collective | D12: Youth Music | E12: Payment blocked | F12: Tranche 2 (£6,250) was due 01 Sep 2026; waiting for interim report | G12: 46266 | H12: 27 | I12: 6250 | J12: Tom B | K12: Chase interim report; hold payment until received | L12: No
A13: High | B13: HF-102 | C13: Mercy Street Food Bank | D13: Hardship Fund | E13: Payment blocked | F13: Tranche 1 (£1,500) due 30 Sep 2026; waiting for agreement | G13: 46295 | I13: 1500 | J13: Sarah J | K13: Chase agreement; hold payment until received | L13: No
A14: High | B14: CAP-7 | C14: Riverside Scout Group | D14: Capital Grants | E14: Payment blocked | F14: Tranche 3 (£20,000) due 01 Oct 2026; waiting for condition | G14: 46296 | I14: 20000 | J14: Priya K | K14: Chase condition; hold payment until received | L14: No
A15: High | B15: YM26/01 | C15: Brass for All | D15: Youth Music | E15: Payment blocked | F15: Tranche 2 (£5,000) due 01 Oct 2026; waiting for interim report | G15: 46296 | I15: 5000 | J15: Tom B | K15: Chase interim report; hold payment until received | L15: No
A16: High | B16: CF-2025-014 | C16: Harbour Youth Project CIO | D16: Community Fund | E16: Payment blocked | F16: Tranche 2 (£10,000) due 21 Oct 2026; waiting for interim report + evidence | G16: 46316 | I16: 10000 | J16: Sarah J | K16: Chase interim report + evidence; hold payment until received | L16: No
A17: High | B17: CF-2026-005 | C17: Greenway Allotment Society | D17: Community Fund | E17: Final report overdue | F17: Final report was due 01 Sep 2026 | G17: 46266 | H17: 27 | J17: — | K17: Chase the report, agree a new date or escalate | L17: No
A18: High | B18: YM25/09 | C18: Rhythm & Roots Drumming | D18: Youth Music | E18: Interim report overdue | F18: Interim report was due 10 Apr 2026 | G18: 46122 | H18: 171 | J18: Tom B | K18: Chase the report, agree a new date or escalate | L18: No
A19: High | B19: YM25/03 | C19: Northgate Music Collective | D19: Youth Music | E19: Interim report overdue | F19: Interim report was due 31 Jul 2026 | G19: 46234 | H19: 59 | J19: Tom B | K19: Chase the report, agree a new date or escalate | L19: No
A20: High | B20: YM26/01 | C20: Brass for All | D20: Youth Music | E20: Interim report overdue | F20: Interim report was due 15 Sep 2026 | G20: 46280 | H20: 13 | J20: Tom B | K20: Chase the report, agree a new date or escalate | L20: No
A21: Medium | B21: YM25/03 | C21: Northgate Music Collective | D21: Youth Music | E21: Due diligence out of date | F21: Last check 10 Jan 2025 (~20 months) before a further payment | G21: 45667 | J21: Tom B | K21: Refresh the check before the next payment | L21: No
A22: Medium | B22: CF-2025-009 | C22: Harbour Youth Proj. | D22: Community Fund | E22: Final report due soon | F22: Final report due 30 Sep 2026 (2 days) | G22: 46295 | J22: Sarah J | K22: Send a reminder now | L22: No
A23: Medium | B23: CF-2025-014 | C23: Harbour Youth Project CIO | D23: Community Fund | E23: Interim report due soon | F23: Interim report due 14 Oct 2026 (16 days) | G23: 46309 | J23: Sarah J | K23: Send a reminder now | L23: No
A24: Medium | C24: Friends of Castle Park | E24: Awarded but not set up | F24: approved at Sept trustees - letter not sent yet | I24: 5000 | J24: — | K24: Send the award letter/agreement and create the grant record | L24: No
A25: Medium | B25: CAP-7 | C25: Riverside Scout Group | D25: Capital Grants | E25: Condition open | F25: Planning permission evidence before tranche 3 | J25: Priya K | K25: Confirm when it will be met | L25: No
A26: Medium | B26: CAP-7 | C26: Riverside Scout Group | D26: Capital Grants | E26: Evidence partial | F26: contractor invoices - some received | J26: Priya K | K26: Request the outstanding evidence | L26: No
A27: Medium | B27: CAP-8 | C27: Eastfield Village Hall | D27: Capital Grants | E27: Evidence missing | F27: completion certificate + photos | J27: Priya K | K27: Request the outstanding evidence | L27: No
A28: Medium | B28: CF-2025-009 | C28: Harbour Youth Proj. | D28: Community Fund | E28: Due-diligence date unknown | F28: Check ticked but not dated | J28: Sarah J | K28: Record when the check was done and what was checked | L28: No
A29: Medium | B29: CF-2025-014 | C29: Harbour Youth Project CIO | D29: Community Fund | E29: Evidence missing | F29: receipts for tranche 1 spend - not yet | J29: Sarah J | K29: Request the outstanding evidence | L29: No
A30: Medium | B30: CF-2026-005 | C30: Greenway Allotment Society | D30: Community Fund | E30: Evidence missing | F30: photos of new raised beds | J30: — | K30: Request the outstanding evidence | L30: No
A31: Medium | B31: YM25/03 | C31: Northgate Music Collective | D31: Youth Music | E31: Condition open | F31: DBS checks for tutors confirmed before term 2 | J31: Tom B | K31: Confirm when it will be met | L31: No
A32: Low | B32: CF-2025-022 | C32: Northbridge Men's Shed | D32: Community Fund | E32: Due diligence out of date | F32: Last check 20 Sep 2025 (~12 months) | G32: 45920 | J32: Tom B | K32: Refresh before any new award | L32: No
A33: Low | B33: CF-2025-021 | C33: Oakfield Carers Network | D33: Community Fund | E33: Due diligence out of date | F33: Last check 25 Sep 2025 (~12 months) | G33: 45925 | J33: Sarah J | K33: Refresh before any new award | L33: No
A34: Low | B34: CAP-9 | C34: Hilltop Community Cafe | D34: Capital Grants | E34: Ready to close | F34: Ended 30 Jun 2026; final report in; fully paid | G34: 46203 | J34: Priya K | K34: Close the grant and file the record | L34: No

Sheet Payments
A1: Grant ref | B1: Recipient | C1: Tranche | D1: Amount £ | E1: Due date | F1: Released when | G1: Release condition met? | H1: Bank details check | I1: Paid (date) | J1: Status | K1: Days late
A2: CF-2025-014 | B2: Harbour Youth Project CIO | C2: 1 | D2: 15000 | E2: 46204 | F2: Agreement | G2: =IF($A2="","",IF(OR(F2="None",F2=""),TRUE,IF(F2="Agreement",INDEX('Grant register'!$J:$J,MATCH($A2,'Grant register'!$A:$A,0))<>"",IF(F2="Due diligence",INDEX('Grant register'!$K:$K,MATCH($A2,'Grant register'!$A:$A,0))<>"",IF(F2="Interim report",INDEX('Grant register'!$O:$O,MATCH($A2,'Grant register'!$A:$A,0))<>"",IF(F2="Final report",INDEX('Grant register'!$Q:$Q,MATCH($A2,'Grant register'!$A:$A,0))<>"",IF(F2="Evidence",INDEX('Grant register'!$S:$S,MATCH($A2,'Grant register'!$A:$A,0))="Received",IF(F2="Condition",INDEX('Grant register'!$M:$M,MATCH($A2,'Grant register'!$A:$A,0))="Yes",IF(F2="Interim report + evidence",AND(INDEX('Grant register'!$O:$O,MATCH($A2,'Grant register'!$A:$A,0))<>"",INDEX('Grant register'!$S:$S,MATCH($A2,'Grant register'!$A:$A,0))="Received"),FALSE))))))))) -> TRUE | H2: OK | I2: yes | J2: =IF($A2="","",IF(I2<>"","Paid",IF(H2="Verify","Blocked: verify bank details",IF(E2="","Due date missing",IF(G2,IF(E2<=TODAY()+30,"Ready for approval","Scheduled"),IF(E2<=TODAY()+30,"Blocked: waiting for "&LOWER(F2),"Waiting: "&LOWER(F2))))))) -> Paid | K2: =IF(OR($A2="",I2<>"",E2="",E2>=TODAY()),"",TODAY()-E2)
A3: CF-2025-014 | B3: Harbour Youth Project CIO | C3: 2 | D3: 10000 | E3: 46316 | F3: Interim report + evidence | G3: =IF($A3="","",IF(OR(F3="None",F3=""),TRUE,IF(F3="Agreement",INDEX('Grant register'!$J:$J,MATCH($A3,'Grant register'!$A:$A,0))<>"",IF(F3="Due diligence",INDEX('Grant register'!$K:$K,MATCH($A3,'Grant register'!$A:$A,0))<>"",IF(F3="Interim report",INDEX('Grant register'!$O:$O,MATCH($A3,'Grant register'!$A:$A,0))<>"",IF(F3="Final report",INDEX('Grant register'!$Q:$Q,MATCH($A3,'Grant register'!$A:$A,0))<>"",IF(F3="Evidence",INDEX('Grant register'!$S:$S,MATCH($A3,'Grant register'!$A:$A,0))="Received",IF(F3="Condition",INDEX('Grant register'!$M:$M,MATCH($A3,'Grant register'!$A:$A,0))="Yes",IF(F3="Interim report + evidence",AND(INDEX('Grant register'!$O:$O,MATCH($A3,'Grant register'!$A:$A,0))<>"",INDEX('Grant register'!$S:$S,MATCH($A3,'Grant register'!$A:$A,0))="Received"),FALSE))))))))) -> FALSE | H3: OK | J3: =IF($A3="","",IF(I3<>"","Paid",IF(H3="Verify","Blocked: verify bank details",IF(E3="","Due date missing",IF(G3,IF(E3<=TODAY()+30,"Ready for approval","Scheduled"),IF(E3<=TODAY()+30,"Blocked: waiting for "&LOWER(F3),"Waiting: "&LOWER(F3))))))) -> Blocked: waiting for interim report + evidence | K3: =IF(OR($A3="",I3<>"",E3="",E3>=TODAY()),"",TODAY()-E3)
A4: CF-2025-009 | B4: Harbour Youth Proj. | C4: 1 | D4: 5000 | E4: 45964 | F4: Agreement | G4: =IF($A4="","",IF(OR(F4="None",F4=""),TRUE,IF(F4="Agreement",INDEX('Grant register'!$J:$J,MATCH($A4,'Grant register'!$A:$A,0))<>"",IF(F4="Due diligence",INDEX('Grant register'!$K:$K,MATCH($A4,'Grant register'!$A:$A,0))<>"",IF(F4="Interim report",INDEX('Grant register'!$O:$O,MATCH($A4,'Grant register'!$A:$A,0))<>"",IF(F4="Final report",INDEX('Grant register'!$Q:$Q,MATCH($A4,'Grant register'!$A:$A,0))<>"",IF(F4="Evidence",INDEX('Grant register'!$S:$S,MATCH($A4,'Grant register'!$A:$A,0))="Received",IF(F4="Condition",INDEX('Grant register'!$M:$M,MATCH($A4,'Grant register'!$A:$A,0))="Yes",IF(F4="Interim report + evidence",AND(INDEX('Grant register'!$O:$O,MATCH($A4,'Grant register'!$A:$A,0))<>"",INDEX('Grant register'!$S:$S,MATCH($A4,'Grant register'!$A:$A,0))="Received"),FALSE))))))))) -> TRUE | H4: OK | I4: yes | J4: =IF($A4="","",IF(I4<>"","Paid",IF(H4="Verify","Blocked: verify bank details",IF(E4="","Due date missing",IF(G4,IF(E4<=TODAY()+30,"Ready for approval","Scheduled"),IF(E4<=TODAY()+30,"Blocked: waiting for "&LOWER(F4),"Waiting: "&LOWER(F4))))))) -> Paid | K4: =IF(OR($A4="",I4<>"",E4="",E4>=TODAY()),"",TODAY()-E4)
A5: YM25/03 | B5: Northgate Music Collective | C5: 1 | D5: 6250 | E5: 46037 | F5: Agreement | G5: =IF($A5="","",IF(OR(F5="None",F5=""),TRUE,IF(F5="Agreement",INDEX('Grant register'!$J:$J,MATCH($A5,'Grant register'!$A:$A,0))<>"",IF(F5="Due diligence",INDEX('Grant register'!$K:$K,MATCH($A5,'Grant register'!$A:$A,0))<>"",IF(F5="Interim report",INDEX('Grant register'!$O:$O,MATCH($A5,'Grant register'!$A:$A,0))<>"",IF(F5="Final report",INDEX('Grant register'!$Q:$Q,MATCH($A5,'Grant register'!$A:$A,0))<>"",IF(F5="Evidence",INDEX('Grant register'!$S:$S,MATCH($A5,'Grant register'!$A:$A,0))="Received",IF(F5="Condition",INDEX('Grant register'!$M:$M,MATCH($A5,'Grant register'!$A:$A,0))="Yes",IF(F5="Interim report + evidence",AND(INDEX('Grant register'!$O:$O,MATCH($A5,'Grant register'!$A:$A,0))<>"",INDEX('Grant register'!$S:$S,MATCH($A5,'Grant register'!$A:$A,0))="Received"),FALSE))))))))) -> TRUE | H5: OK | I5: yes | J5: =IF($A5="","",IF(I5<>"","Paid",IF(H5="Verify","Blocked: verify bank details",IF(E5="","Due date missing",IF(G5,IF(E5<=TODAY()+30,"Ready for approval","Scheduled"),IF(E5<=TODAY()+30,"Blocked: waiting for "&LOWER(F5),"Waiting: "&LOWER(F5))))))) -> Paid | K5: =IF(OR($A5="",I5<>"",E5="",E5>=TODAY()),"",TODAY()-E5)
A6: YM25/03 | B6: Northgate Music Collective | C6: 2 | D6: 6250 | E6: 46266 | F6: Interim report | G6: =IF($A6="","",IF(OR(F6="None",F6=""),TRUE,IF(F6="Agreement",INDEX('Grant register'!$J:$J,MATCH($A6,'Grant register'!$A:$A,0))<>"",IF(F6="Due diligence",INDEX('Grant register'!$K:$K,MATCH($A6,'Grant register'!$A:$A,0))<>"",IF(F6="Interim report",INDEX('Grant register'!$O:$O,MATCH($A6,'Grant register'!$A:$A,0))<>"",IF(F6="Final report",INDEX('Grant register'!$Q:$Q,MATCH($A6,'Grant register'!$A:$A,0))<>"",IF(F6="Evidence",INDEX('Grant register'!$S:$S,MATCH($A6,'Grant register'!$A:$A,0))="Received",IF(F6="Condition",INDEX('Grant register'!$M:$M,MATCH($A6,'Grant register'!$A:$A,0))="Yes",IF(F6="Interim report + evidence",AND(INDEX('Grant register'!$O:$O,MATCH($A6,'Grant register'!$A:$A,0))<>"",INDEX('Grant register'!$S:$S,MATCH($A6,'Grant register'!$A:$A,0))="Received"),FALSE))))))))) -> FALSE | H6: OK | J6: =IF($A6="","",IF(I6<>"","Paid",IF(H6="Verify","Blocked: verify bank details",IF(E6="","Due date missing",IF(G6,IF(E6<=TODAY()+30,"Ready for approval","Scheduled"),IF(E6<=TODAY()+30,"Blocked: waiting for "&LOWER(F6),"Waiting: "&LOWER(F6))))))) -> Blocked: waiting for interim report | K6: =IF(OR($A6="",I6<>"",E6="",E6>=TODAY()),"",TODAY()-E6) -> 27
A7: YM25/05 | B7: St Anne's Community Choir | C7: 1 | D7: 3000 | E7: 46086 | F7: Agreement | G7: =IF($A7="","",IF(OR(F7="None",F7=""),TRUE,IF(F7="Agreement",INDEX('Grant register'!$J:$J,MATCH($A7,'Grant register'!$A:$A,0))<>"",IF(F7="Due diligence",INDEX('Grant register'!$K:$K,MATCH($A7,'Grant register'!$A:$A,0))<>"",IF(F7="Interim report",INDEX('Grant register'!$O:$O,MATCH($A7,'Grant register'!$A:$A,0))<>"",IF(F7="Final report",INDEX('Grant register'!$Q:$Q,MATCH($A7,'Grant register'!$A:$A,0))<>"",IF(F7="Evidence",INDEX('Grant register'!$S:$S,MATCH($A7,'Grant register'!$A:$A,0))="Received",IF(F7="Condition",INDEX('Grant register'!$M:$M,MATCH($A7,'Grant register'!$A:$A,0))="Yes",IF(F7="Interim report + evidence",AND(INDEX('Grant register'!$O:$O,MATCH($A7,'Grant register'!$A:$A,0))<>"",INDEX('Grant register'!$S:$S,MATCH($A7,'Grant register'!$A:$A,0))="Received"),FALSE))))))))) -> FALSE | H7: OK | I7: yes | J7: =IF($A7="","",IF(I7<>"","Paid",IF(H7="Verify","Blocked: verify bank details",IF(E7="","Due date missing",IF(G7,IF(E7<=TODAY()+30,"Ready for approval","Scheduled"),IF(E7<=TODAY()+30,"Blocked: waiting for "&LOWER(F7),"Waiting: "&LOWER(F7))))))) -> Paid | K7: =IF(OR($A7="",I7<>"",E7="",E7>=TODAY()),"",TODAY()-E7)
A8: CAP-7 | B8: Riverside Scout Group | C8: 1 | D8: 10000 | E8: 46034 | F8: Agreement | G8: =IF($A8="","",IF(OR(F8="None",F8=""),TRUE,IF(F8="Agreement",INDEX('Grant register'!$J:$J,MATCH($A8,'Grant register'!$A:$A,0))<>"",IF(F8="Due diligence",INDEX('Grant register'!$K:$K,MATCH($A8,'Grant register'!$A:$A,0))<>"",IF(F8="Interim report",INDEX('Grant register'!$O:$O,MATCH($A8,'Grant register'!$A:$A,0))<>"",IF(F8="Final report",INDEX('Grant register'!$Q:$Q,MATCH($A8,'Grant register'!$A:$A,0))<>"",IF(F8="Evidence",INDEX('Grant register'!$S:$S,MATCH($A8,'Grant register'!$A:$A,0))="Received",IF(F8="Condition",INDEX('Grant register'!$M:$M,MATCH($A8,'Grant register'!$A:$A,0))="Yes",IF(F8="Interim report + evidence",AND(INDEX('Grant register'!$O:$O,MATCH($A8,'Grant register'!$A:$A,0))<>"",INDEX('Grant register'!$S:$S,MATCH($A8,'Grant register'!$A:$A,0))="Received"),FALSE))))))))) -> TRUE | H8: OK | I8: yes | J8: =IF($A8="","",IF(I8<>"","Paid",IF(H8="Verify","Blocked: verify bank details",IF(E8="","Due date missing",IF(G8,IF(E8<=TODAY()+30,"Ready for approval","Scheduled"),IF(E8<=TODAY()+30,"Blocked: waiting for "&LOWER(F8),"Waiting: "&LOWER(F8))))))) -> Paid | K8: =IF(OR($A8="",I8<>"",E8="",E8>=TODAY()),"",TODAY()-E8)
A9: CAP-7 | B9: Riverside Scout Group | C9: 2 | D9: 10000 | E9: 46113 | F9: Agreement | G9: =IF($A9="","",IF(OR(F9="None",F9=""),TRUE,IF(F9="Agreement",INDEX('Grant register'!$J:$J,MATCH($A9,'Grant register'!$A:$A,0))<>"",IF(F9="Due diligence",INDEX('Grant register'!$K:$K,MATCH($A9,'Grant register'!$A:$A,0))<>"",IF(F9="Interim report",INDEX('Grant register'!$O:$O,MATCH($A9,'Grant register'!$A:$A,0))<>"",IF(F9="Final report",INDEX('Grant register'!$Q:$Q,MATCH($A9,'Grant register'!$A:$A,0))<>"",IF(F9="Evidence",INDEX('Grant register'!$S:$S,MATCH($A9,'Grant register'!$A:$A,0))="Received",IF(F9="Condition",INDEX('Grant register'!$M:$M,MATCH($A9,'Grant register'!$A:$A,0))="Yes",IF(F9="Interim report + evidence",AND(INDEX('Grant register'!$O:$O,MATCH($A9,'Grant register'!$A:$A,0))<>"",INDEX('Grant register'!$S:$S,MATCH($A9,'Grant register'!$A:$A,0))="Received"),FALSE))))))))) -> TRUE | H9: OK | I9: yes | J9: =IF($A9="","",IF(I9<>"","Paid",IF(H9="Verify","Blocked: verify bank details",IF(E9="","Due date missing",IF(G9,IF(E9<=TODAY()+30,"Ready for approval","Scheduled"),IF(E9<=TODAY()+30,"Blocked: waiting for "&LOWER(F9),"Waiting: "&LOWER(F9))))))) -> Paid | K9: =IF(OR($A9="",I9<>"",E9="",E9>=TODAY()),"",TODAY()-E9)
A10: CAP-7 | B10: Riverside Scout Group | C10: 3 | D10: 20000 | E10: 46296 | F10: Condition | G10: =IF($A10="","",IF(OR(F10="None",F10=""),TRUE,IF(F10="Agreement",INDEX('Grant register'!$J:$J,MATCH($A10,'Grant register'!$A:$A,0))<>"",IF(F10="Due diligence",INDEX('Grant register'!$K:$K,MATCH($A10,'Grant register'!$A:$A,0))<>"",IF(F10="Interim report",INDEX('Grant register'!$O:$O,MATCH($A10,'Grant register'!$A:$A,0))<>"",IF(F10="Final report",INDEX('Grant register'!$Q:$Q,MATCH($A10,'Grant register'!$A:$A,0))<>"",IF(F10="Evidence",INDEX('Grant register'!$S:$S,MATCH($A10,'Grant register'!$A:$A,0))="Received",IF(F10="Condition",INDEX('Grant register'!$M:$M,MATCH($A10,'Grant register'!$A:$A,0))="Yes",IF(F10="Interim report + evidence",AND(INDEX('Grant register'!$O:$O,MATCH($A10,'Grant register'!$A:$A,0))<>"",INDEX('Grant register'!$S:$S,MATCH($A10,'Grant register'!$A:$A,0))="Received"),FALSE))))))))) -> FALSE | H10: OK | J10: =IF($A10="","",IF(I10<>"","Paid",IF(H10="Verify","Blocked: verify bank details",IF(E10="","Due date missing",IF(G10,IF(E10<=TODAY()+30,"Ready for approval","Scheduled"),IF(E10<=TODAY()+30,"Blocked: waiting for "&LOWER(F10),"Waiting: "&LOWER(F10))))))) -> Blocked: waiting for condition | K10: =IF(OR($A10="",I10<>"",E10="",E10>=TODAY()),"",TODAY()-E10)
A11: CAP-8 | B11: Eastfield Village Hall | C11: 1 | D11: 9000 | E11: 46073 | F11: Agreement | G11: =IF($A11="","",IF(OR(F11="None",F11=""),TRUE,IF(F11="Agreement",INDEX('Grant register'!$J:$J,MATCH($A11,'Grant register'!$A:$A,0))<>"",IF(F11="Due diligence",INDEX('Grant register'!$K:$K,MATCH($A11,'Grant register'!$A:$A,0))<>"",IF(F11="Interim report",INDEX('Grant register'!$O:$O,MATCH($A11,'Grant register'!$A:$A,0))<>"",IF(F11="Final report",INDEX('Grant register'!$Q:$Q,MATCH($A11,'Grant register'!$A:$A,0))<>"",IF(F11="Evidence",INDEX('Grant register'!$S:$S,MATCH($A11,'Grant register'!$A:$A,0))="Received",IF(F11="Condition",INDEX('Grant register'!$M:$M,MATCH($A11,'Grant register'!$A:$A,0))="Yes",IF(F11="Interim report + evidence",AND(INDEX('Grant register'!$O:$O,MATCH($A11,'Grant register'!$A:$A,0))<>"",INDEX('Grant register'!$S:$S,MATCH($A11,'Grant register'!$A:$A,0))="Received"),FALSE))))))))) -> TRUE | H11: OK | I11: yes | J11: =IF($A11="","",IF(I11<>"","Paid",IF(H11="Verify","Blocked: verify bank details",IF(E11="","Due date missing",IF(G11,IF(E11<=TODAY()+30,"Ready for approval","Scheduled"),IF(E11<=TODAY()+30,"Blocked: waiting for "&LOWER(F11),"Waiting: "&LOWER(F11))))))) -> Paid | K11: =IF(OR($A11="",I11<>"",E11="",E11>=TODAY()),"",TODAY()-E11)
A12: CAP-8 | B12: Eastfield Village Hall | C12: 2 | D12: 9000 | E12: 46326 | F12: Evidence | G12: =IF($A12="","",IF(OR(F12="None",F12=""),TRUE,IF(F12="Agreement",INDEX('Grant register'!$J:$J,MATCH($A12,'Grant register'!$A:$A,0))<>"",IF(F12="Due diligence",INDEX('Grant register'!$K:$K,MATCH($A12,'Grant register'!$A:$A,0))<>"",IF(F12="Interim report",INDEX('Grant register'!$O:$O,MATCH($A12,'Grant register'!$A:$A,0))<>"",IF(F12="Final report",INDEX('Grant register'!$Q:$Q,MATCH($A12,'Grant register'!$A:$A,0))<>"",IF(F12="Evidence",INDEX('Grant register'!$S:$S,MATCH($A12,'Grant register'!$A:$A,0))="Received",IF(F12="Condition",INDEX('Grant register'!$M:$M,MATCH($A12,'Grant register'!$A:$A,0))="Yes",IF(F12="Interim report + evidence",AND(INDEX('Grant register'!$O:$O,MATCH($A12,'Grant register'!$A:$A,0))<>"",INDEX('Grant register'!$S:$S,MATCH($A12,'Grant register'!$A:$A,0))="Received"),FALSE))))))))) -> FALSE | H12: Verify | J12: =IF($A12="","",IF(I12<>"","Paid",IF(H12="Verify","Blocked: verify bank details",IF(E12="","Due date missing",IF(G12,IF(E12<=TODAY()+30,"Ready for approval","Scheduled"),IF(E12<=TODAY()+30,"Blocked: waiting for "&LOWER(F12),"Waiting: "&LOWER(F12))))))) -> Blocked: verify bank details | K12: =IF(OR($A12="",I12<>"",E12="",E12>=TODAY()),"",TODAY()-E12)
A13: HF-101 | B13: Mercy Street Food Bank | C13: 1 | D13: 2500 | E13: 46266 | F13: Agreement | G13: =IF($A13="","",IF(OR(F13="None",F13=""),TRUE,IF(F13="Agreement",INDEX('Grant register'!$J:$J,MATCH($A13,'Grant register'!$A:$A,0))<>"",IF(F13="Due diligence",INDEX('Grant register'!$K:$K,MATCH($A13,'Grant register'!$A:$A,0))<>"",IF(F13="Interim report",INDEX('Grant register'!$O:$O,MATCH($A13,'Grant register'!$A:$A,0))<>"",IF(F13="Final report",INDEX('Grant register'!$Q:$Q,MATCH($A13,'Grant register'!$A:$A,0))<>"",IF(F13="Evidence",INDEX('Grant register'!$S:$S,MATCH($A13,'Grant register'!$A:$A,0))="Received",IF(F13="Condition",INDEX('Grant register'!$M:$M,MATCH($A13,'Grant register'!$A:$A,0))="Yes",IF(F13="Interim report + evidence",AND(INDEX('Grant register'!$O:$O,MATCH($A13,'Grant register'!$A:$A,0))<>"",INDEX('Grant register'!$S:$S,MATCH($A13,'Grant register'!$A:$A,0))="Received"),FALSE))))))))) -> TRUE | H13: OK | I13: yes | J13: =IF($A13="","",IF(I13<>"","Paid",IF(H13="Verify","Blocked: verify bank details",IF(E13="","Due date missing",IF(G13,IF(E13<=TODAY()+30,"Ready for approval","Scheduled"),IF(E13<=TODAY()+30,"Blocked: waiting for "&LOWER(F13),"Waiting: "&LOWER(F13))))))) -> Paid | K13: =IF(OR($A13="",I13<>"",E13="",E13>=TODAY()),"",TODAY()-E13)
A14: HF-102 | B14: Mercy Street Food Bank | C14: 1 | D14: 1500 | E14: 46295 | F14: Agreement | G14: =IF($A14="","",IF(OR(F14="None",F14=""),TRUE,IF(F14="Agreement",INDEX('Grant register'!$J:$J,MATCH($A14,'Grant register'!$A:$A,0))<>"",IF(F14="Due diligence",INDEX('Grant register'!$K:$K,MATCH($A14,'Grant register'!$A:$A,0))<>"",IF(F14="Interim report",INDEX('Grant register'!$O:$O,MATCH($A14,'Grant register'!$A:$A,0))<>"",IF(F14="Final report",INDEX('Grant register'!$Q:$Q,MATCH($A14,'Grant register'!$A:$A,0))<>"",IF(F14="Evidence",INDEX('Grant register'!$S:$S,MATCH($A14,'Grant register'!$A:$A,0))="Received",IF(F14="Condition",INDEX('Grant register'!$M:$M,MATCH($A14,'Grant register'!$A:$A,0))="Yes",IF(F14="Interim report + evidence",AND(INDEX('Grant register'!$O:$O,MATCH($A14,'Grant register'!$A:$A,0))<>"",INDEX('Grant register'!$S:$S,MATCH($A14,'Grant register'!$A:$A,0))="Received"),FALSE))))))))) -> FALSE | H14: OK | J14: =IF($A14="","",IF(I14<>"","Paid",IF(H14="Verify","Blocked: verify bank details",IF(E14="","Due date missing",IF(G14,IF(E14<=TODAY()+30,"Ready for approval","Scheduled"),IF(E14<=TODAY()+30,"Blocked: waiting for "&LOWER(F14),"Waiting: "&LOWER(F14))))))) -> Blocked: waiting for agreement | K14: =IF(OR($A14="",I14<>"",E14="",E14>=TODAY()),"",TODAY()-E14)
A15: CF-2026-002 | B15: Lanterns Mental Health Peer Support | C15: 1 | D15: 15000 | E15: 46063 | F15: Agreement | G15: =IF($A15="","",IF(OR(F15="None",F15=""),TRUE,IF(F15="Agreement",INDEX('Grant register'!$J:$J,MATCH($A15,'Grant register'!$A:$A,0))<>"",IF(F15="Due diligence",INDEX('Grant register'!$K:$K,MATCH($A15,'Grant register'!$A:$A,0))<>"",IF(F15="Interim report",INDEX('Grant register'!$O:$O,MATCH($A15,'Grant register'!$A:$A,0))<>"",IF(F15="Final report",INDEX('Grant register'!$Q:$Q,MATCH($A15,'Grant register'!$A:$A,0))<>"",IF(F15="Evidence",INDEX('Grant register'!$S:$S,MATCH($A15,'Grant register'!$A:$A,0))="Received",IF(F15="Condition",INDEX('Grant register'!$M:$M,MATCH($A15,'Grant register'!$A:$A,0))="Yes",IF(F15="Interim report + evidence",AND(INDEX('Grant register'!$O:$O,MATCH($A15,'Grant register'!$A:$A,0))<>"",INDEX('Grant register'!$S:$S,MATCH($A15,'Grant register'!$A:$A,0))="Received"),FALSE))))))))) -> TRUE | H15: OK | I15: yes | J15: =IF($A15="","",IF(I15<>"","Paid",IF(H15="Verify","Blocked: verify bank details",IF(E15="","Due date missing",IF(G15,IF(E15<=TODAY()+30,"Ready for approval","Scheduled"),IF(E15<=TODAY()+30,"Blocked: waiting for "&LOWER(F15),"Waiting: "&LOWER(F15))))))) -> Paid | K15: =IF(OR($A15="",I15<>"",E15="",E15>=TODAY()),"",TODAY()-E15)
A16: CF-2026-002 | B16: Lanterns Mental Health Peer Support | C16: 2 | D16: 15000 | E16: 46275 | F16: Interim report | G16: =IF($A16="","",IF(OR(F16="None",F16=""),TRUE,IF(F16="Agreement",INDEX('Grant register'!$J:$J,MATCH($A16,'Grant register'!$A:$A,0))<>"",IF(F16="Due diligence",INDEX('Grant register'!$K:$K,MATCH($A16,'Grant register'!$A:$A,0))<>"",IF(F16="Interim report",INDEX('Grant register'!$O:$O,MATCH($A16,'Grant register'!$A:$A,0))<>"",IF(F16="Final report",INDEX('Grant register'!$Q:$Q,MATCH($A16,'Grant register'!$A:$A,0))<>"",IF(F16="Evidence",INDEX('Grant register'!$S:$S,MATCH($A16,'Grant register'!$A:$A,0))="Received",IF(F16="Condition",INDEX('Grant register'!$M:$M,MATCH($A16,'Grant register'!$A:$A,0))="Yes",IF(F16="Interim report + evidence",AND(INDEX('Grant register'!$O:$O,MATCH($A16,'Grant register'!$A:$A,0))<>"",INDEX('Grant register'!$S:$S,MATCH($A16,'Grant register'!$A:$A,0))="Received"),FALSE))))))))) -> TRUE | H16: OK | J16: =IF($A16="","",IF(I16<>"","Paid",IF(H16="Verify","Blocked: verify bank details",IF(E16="","Due date missing",IF(G16,IF(E16<=TODAY()+30,"Ready for approval","Scheduled"),IF(E16<=TODAY()+30,"Blocked: waiting for "&LOWER(F16),"Waiting: "&LOWER(F16))))))) -> Ready for approval | K16: =IF(OR($A16="",I16<>"",E16="",E16>=TODAY()),"",TODAY()-E16) -> 18
A17: CF-2026-005 | B17: Greenway Allotment Society | C17: 1 | D17: 4000 | E17: 46115 | F17: Agreement | G17: =IF($A17="","",IF(OR(F17="None",F17=""),TRUE,IF(F17="Agreement",INDEX('Grant register'!$J:$J,MATCH($A17,'Grant register'!$A:$A,0))<>"",IF(F17="Due diligence",INDEX('Grant register'!$K:$K,MATCH($A17,'Grant register'!$A:$A,0))<>"",IF(F17="Interim report",INDEX('Grant register'!$O:$O,MATCH($A17,'Grant register'!$A:$A,0))<>"",IF(F17="Final report",INDEX('Grant register'!$Q:$Q,MATCH($A17,'Grant register'!$A:$A,0))<>"",IF(F17="Evidence",INDEX('Grant register'!$S:$S,MATCH($A17,'Grant register'!$A:$A,0))="Received",IF(F17="Condition",INDEX('Grant register'!$M:$M,MATCH($A17,'Grant register'!$A:$A,0))="Yes",IF(F17="Interim report + evidence",AND(INDEX('Grant register'!$O:$O,MATCH($A17,'Grant register'!$A:$A,0))<>"",INDEX('Grant register'!$S:$S,MATCH($A17,'Grant register'!$A:$A,0))="Received"),FALSE))))))))) -> TRUE | H17: OK | I17: yes | J17: =IF($A17="","",IF(I17<>"","Paid",IF(H17="Verify","Blocked: verify bank details",IF(E17="","Due date missing",IF(G17,IF(E17<=TODAY()+30,"Ready for approval","Scheduled"),IF(E17<=TODAY()+30,"Blocked: waiting for "&LOWER(F17),"Waiting: "&LOWER(F17))))))) -> Paid | K17: =IF(OR($A17="",I17<>"",E17="",E17>=TODAY()),"",TODAY()-E17)
A18: CF-2026-007 | B18: Kids Code Club Northbridge | C18: 1 | D18: 4000 | E18: 46143 | F18: Agreement | G18: =IF($A18="","",IF(OR(F18="None",F18=""),TRUE,IF(F18="Agreement",INDEX('Grant register'!$J:$J,MATCH($A18,'Grant register'!$A:$A,0))<>"",IF(F18="Due diligence",INDEX('Grant register'!$K:$K,MATCH($A18,'Grant register'!$A:$A,0))<>"",IF(F18="Interim report",INDEX('Grant register'!$O:$O,MATCH($A18,'Grant register'!$A:$A,0))<>"",IF(F18="Final report",INDEX('Grant register'!$Q:$Q,MATCH($A18,'Grant register'!$A:$A,0))<>"",IF(F18="Evidence",INDEX('Grant register'!$S:$S,MATCH($A18,'Grant register'!$A:$A,0))="Received",IF(F18="Condition",INDEX('Grant register'!$M:$M,MATCH($A18,'Grant register'!$A:$A,0))="Yes",IF(F18="Interim report + evidence",AND(INDEX('Grant register'!$O:$O,MATCH($A18,'Grant register'!$A:$A,0))<>"",INDEX('Grant register'!$S:$S,MATCH($A18,'Grant register'!$A:$A,0))="Received"),FALSE))))))))) -> TRUE | H18: OK | I18: yes | J18: =IF($A18="","",IF(I18<>"","Paid",IF(H18="Verify","Blocked: verify bank details",IF(E18="","Due date missing",IF(G18,IF(E18<=TODAY()+30,"Ready for approval","Scheduled"),IF(E18<=TODAY()+30,"Blocked: waiting for "&LOWER(F18),"Waiting: "&LOWER(F18))))))) -> Paid | K18: =IF(OR($A18="",I18<>"",E18="",E18>=TODAY()),"",TODAY()-E18)
A19: CF-2026-007 | B19: Kids Code Club Northbridge | C19: 2 | D19: 4000 | E19: 46357 | F19: Interim report | G19: =IF($A19="","",IF(OR(F19="None",F19=""),TRUE,IF(F19="Agreement",INDEX('Grant register'!$J:$J,MATCH($A19,'Grant register'!$A:$A,0))<>"",IF(F19="Due diligence",INDEX('Grant register'!$K:$K,MATCH($A19,'Grant register'!$A:$A,0))<>"",IF(F19="Interim report",INDEX('Grant register'!$O:$O,MATCH($A19,'Grant register'!$A:$A,0))<>"",IF(F19="Final report",INDEX('Grant register'!$Q:$Q,MATCH($A19,'Grant register'!$A:$A,0))<>"",IF(F19="Evidence",INDEX('Grant register'!$S:$S,MATCH($A19,'Grant register'!$A:$A,0))="Received",IF(F19="Condition",INDEX('Grant register'!$M:$M,MATCH($A19,'Grant register'!$A:$A,0))="Yes",IF(F19="Interim report + evidence",AND(INDEX('Grant register'!$O:$O,MATCH($A19,'Grant register'!$A:$A,0))<>"",INDEX('Grant register'!$S:$S,MATCH($A19,'Grant register'!$A:$A,0))="Received"),FALSE))))))))) -> FALSE | H19: OK | J19: =IF($A19="","",IF(I19<>"","Paid",IF(H19="Verify","Blocked: verify bank details",IF(E19="","Due date missing",IF(G19,IF(E19<=TODAY()+30,"Ready for approval","Scheduled"),IF(E19<=TODAY()+30,"Blocked: waiting for "&LOWER(F19),"Waiting: "&LOWER(F19))))))) -> Waiting: interim report | K19: =IF(OR($A19="",I19<>"",E19="",E19>=TODAY()),"",TODAY()-E19)
A20: YM26/01 | B20: Brass for All | C20: 1 | D20: 5000 | E20: 46174 | F20: Agreement | G20: =IF($A20="","",IF(OR(F20="None",F20=""),TRUE,IF(F20="Agreement",INDEX('Grant register'!$J:$J,MATCH($A20,'Grant register'!$A:$A,0))<>"",IF(F20="Due diligence",INDEX('Grant register'!$K:$K,MATCH($A20,'Grant register'!$A:$A,0))<>"",IF(F20="Interim report",INDEX('Grant register'!$O:$O,MATCH($A20,'Grant register'!$A:$A,0))<>"",IF(F20="Final report",INDEX('Grant register'!$Q:$Q,MATCH($A20,'Grant register'!$A:$A,0))<>"",IF(F20="Evidence",INDEX('Grant register'!$S:$S,MATCH($A20,'Grant register'!$A:$A,0))="Received",IF(F20="Condition",INDEX('Grant register'!$M:$M,MATCH($A20,'Grant register'!$A:$A,0))="Yes",IF(F20="Interim report + evidence",AND(INDEX('Grant register'!$O:$O,MATCH($A20,'Grant register'!$A:$A,0))<>"",INDEX('Grant register'!$S:$S,MATCH($A20,'Grant register'!$A:$A,0))="Received"),FALSE))))))))) -> TRUE | H20: OK | I20: yes | J20: =IF($A20="","",IF(I20<>"","Paid",IF(H20="Verify","Blocked: verify bank details",IF(E20="","Due date missing",IF(G20,IF(E20<=TODAY()+30,"Ready for approval","Scheduled"),IF(E20<=TODAY()+30,"Blocked: waiting for "&LOWER(F20),"Waiting: "&LOWER(F20))))))) -> Paid | K20: =IF(OR($A20="",I20<>"",E20="",E20>=TODAY()),"",TODAY()-E20)
A21: YM26/01 | B21: Brass for All | C21: 2 | D21: 5000 | E21: 46296 | F21: Interim report | G21: =IF($A21="","",IF(OR(F21="None",F21=""),TRUE,IF(F21="Agreement",INDEX('Grant register'!$J:$J,MATCH($A21,'Grant register'!$A:$A,0))<>"",IF(F21="Due diligence",INDEX('Grant register'!$K:$K,MATCH($A21,'Grant register'!$A:$A,0))<>"",IF(F21="Interim report",INDEX('Grant register'!$O:$O,MATCH($A21,'Grant register'!$A:$A,0))<>"",IF(F21="Final report",INDEX('Grant register'!$Q:$Q,MATCH($A21,'Grant register'!$A:$A,0))<>"",IF(F21="Evidence",INDEX('Grant register'!$S:$S,MATCH($A21,'Grant register'!$A:$A,0))="Received",IF(F21="Condition",INDEX('Grant register'!$M:$M,MATCH($A21,'Grant register'!$A:$A,0))="Yes",IF(F21="Interim report + evidence",AND(INDEX('Grant register'!$O:$O,MATCH($A21,'Grant register'!$A:$A,0))<>"",INDEX('Grant register'!$S:$S,MATCH($A21,'Grant register'!$A:$A,0))="Received"),FALSE))))))))) -> FALSE | H21: OK | J21: =IF($A21="","",IF(I21<>"","Paid",IF(H21="Verify","Blocked: verify bank details",IF(E21="","Due date missing",IF(G21,IF(E21<=TODAY()+30,"Ready for approval","Scheduled"),IF(E21<=TODAY()+30,"Blocked: waiting for "&LOWER(F21),"Waiting: "&LOWER(F21))))))) -> Blocked: waiting for interim report | K21: =IF(OR($A21="",I21<>"",E21="",E21>=TODAY()),"",TODAY()-E21)
A22: YM26/01 | B22: Brass for All | C22: 3 | D22: 5000 | E22: 46419 | F22: Condition | G22: =IF($A22="","",IF(OR(F22="None",F22=""),TRUE,IF(F22="Agreement",INDEX('Grant register'!$J:$J,MATCH($A22,'Grant register'!$A:$A,0))<>"",IF(F22="Due diligence",INDEX('Grant register'!$K:$K,MATCH($A22,'Grant register'!$A:$A,0))<>"",IF(F22="Interim report",INDEX('Grant register'!$O:$O,MATCH($A22,'Grant register'!$A:$A,0))<>"",IF(F22="Final report",INDEX('Grant register'!$Q:$Q,MATCH($A22,'Grant register'!$A:$A,0))<>"",IF(F22="Evidence",INDEX('Grant register'!$S:$S,MATCH($A22,'Grant register'!$A:$A,0))="Received",IF(F22="Condition",INDEX('Grant register'!$M:$M,MATCH($A22,'Grant register'!$A:$A,0))="Yes",IF(F22="Interim report + evidence",AND(INDEX('Grant register'!$O:$O,MATCH($A22,'Grant register'!$A:$A,0))<>"",INDEX('Grant register'!$S:$S,MATCH($A22,'Grant register'!$A:$A,0))="Received"),FALSE))))))))) -> FALSE | H22: OK | J22: =IF($A22="","",IF(I22<>"","Paid",IF(H22="Verify","Blocked: verify bank details",IF(E22="","Due date missing",IF(G22,IF(E22<=TODAY()+30,"Ready for approval","Scheduled"),IF(E22<=TODAY()+30,"Blocked: waiting for "&LOWER(F22),"Waiting: "&LOWER(F22))))))) -> Waiting: condition | K22: =IF(OR($A22="",I22<>"",E22="",E22>=TODAY()),"",TODAY()-E22)
A23: YM26/02 | B23: The Beat Box Studio CIC | C23: 1 | D23: 9500 | E23: 46193 | F23: Agreement | G23: =IF($A23="","",IF(OR(F23="None",F23=""),TRUE,IF(F23="Agreement",INDEX('Grant register'!$J:$J,MATCH($A23,'Grant register'!$A:$A,0))<>"",IF(F23="Due diligence",INDEX('Grant register'!$K:$K,MATCH($A23,'Grant register'!$A:$A,0))<>"",IF(F23="Interim report",INDEX('Grant register'!$O:$O,MATCH($A23,'Grant register'!$A:$A,0))<>"",IF(F23="Final report",INDEX('Grant register'!$Q:$Q,MATCH($A23,'Grant register'!$A:$A,0))<>"",IF(F23="Evidence",INDEX('Grant register'!$S:$S,MATCH($A23,'Grant register'!$A:$A,0))="Received",IF(F23="Condition",INDEX('Grant register'!$M:$M,MATCH($A23,'Grant register'!$A:$A,0))="Yes",IF(F23="Interim report + evidence",AND(INDEX('Grant register'!$O:$O,MATCH($A23,'Grant register'!$A:$A,0))<>"",INDEX('Grant register'!$S:$S,MATCH($A23,'Grant register'!$A:$A,0))="Received"),FALSE))))))))) -> TRUE | H23: OK | I23: yes | J23: =IF($A23="","",IF(I23<>"","Paid",IF(H23="Verify","Blocked: verify bank details",IF(E23="","Due date missing",IF(G23,IF(E23<=TODAY()+30,"Ready for approval","Scheduled"),IF(E23<=TODAY()+30,"Blocked: waiting for "&LOWER(F23),"Waiting: "&LOWER(F23))))))) -> Paid | K23: =IF(OR($A23="",I23<>"",E23="",E23>=TODAY()),"",TODAY()-E23)
A24: CAP-9 | B24: Hilltop Community Cafe | C24: 1 | D24: 11000 | E24: 46003 | F24: Agreement | G24: =IF($A24="","",IF(OR(F24="None",F24=""),TRUE,IF(F24="Agreement",INDEX('Grant register'!$J:$J,MATCH($A24,'Grant register'!$A:$A,0))<>"",IF(F24="Due diligence",INDEX('Grant register'!$K:$K,MATCH($A24,'Grant register'!$A:$A,0))<>"",IF(F24="Interim report",INDEX('Grant register'!$O:$O,MATCH($A24,'Grant register'!$A:$A,0))<>"",IF(F24="Final report",INDEX('Grant register'!$Q:$Q,MATCH($A24,'Grant register'!$A:$A,0))<>"",IF(F24="Evidence",INDEX('Grant register'!$S:$S,MATCH($A24,'Grant register'!$A:$A,0))="Received",IF(F24="Condition",INDEX('Grant register'!$M:$M,MATCH($A24,'Grant register'!$A:$A,0))="Yes",IF(F24="Interim report + evidence",AND(INDEX('Grant register'!$O:$O,MATCH($A24,'Grant register'!$A:$A,0))<>"",INDEX('Grant register'!$S:$S,MATCH($A24,'Grant register'!$A:$A,0))="Received"),FALSE))))))))) -> TRUE | H24: OK | I24: yes | J24: =IF($A24="","",IF(I24<>"","Paid",IF(H24="Verify","Blocked: verify bank details",IF(E24="","Due date missing",IF(G24,IF(E24<=TODAY()+30,"Ready for approval","Scheduled"),IF(E24<=TODAY()+30,"Blocked: waiting for "&LOWER(F24),"Waiting: "&LOWER(F24))))))) -> Paid | K24: =IF(OR($A24="",I24<>"",E24="",E24>=TODAY()),"",TODAY()-E24)
A25: CAP-9 | B25: Hilltop Community Cafe | C25: 2 | D25: 11000 | E25: 46203 | F25: Final report | G25: =IF($A25="","",IF(OR(F25="None",F25=""),TRUE,IF(F25="Agreement",INDEX('Grant register'!$J:$J,MATCH($A25,'Grant register'!$A:$A,0))<>"",IF(F25="Due diligence",INDEX('Grant register'!$K:$K,MATCH($A25,'Grant register'!$A:$A,0))<>"",IF(F25="Interim report",INDEX('Grant register'!$O:$O,MATCH($A25,'Grant register'!$A:$A,0))<>"",IF(F25="Final report",INDEX('Grant register'!$Q:$Q,MATCH($A25,'Grant register'!$A:$A,0))<>"",IF(F25="Evidence",INDEX('Grant register'!$S:$S,MATCH($A25,'Grant register'!$A:$A,0))="Received",IF(F25="Condition",INDEX('Grant register'!$M:$M,MATCH($A25,'Grant register'!$A:$A,0))="Yes",IF(F25="Interim report + evidence",AND(INDEX('Grant register'!$O:$O,MATCH($A25,'Grant register'!$A:$A,0))<>"",INDEX('Grant register'!$S:$S,MATCH($A25,'Grant register'!$A:$A,0))="Received"),FALSE))))))))) -> TRUE | H25: OK | I25: yes | J25: =IF($A25="","",IF(I25<>"","Paid",IF(H25="Verify","Blocked: verify bank details",IF(E25="","Due date missing",IF(G25,IF(E25<=TODAY()+30,"Ready for approval","Scheduled"),IF(E25<=TODAY()+30,"Blocked: waiting for "&LOWER(F25),"Waiting: "&LOWER(F25))))))) -> Paid | K25: =IF(OR($A25="",I25<>"",E25="",E25>=TODAY()),"",TODAY()-E25)
A26: HF-103 | B26: Westside Refugee Welcome | C26: 1 | D26: 3000 | E26: 46280 | F26: Agreement | G26: =IF($A26="","",IF(OR(F26="None",F26=""),TRUE,IF(F26="Agreement",INDEX('Grant register'!$J:$J,MATCH($A26,'Grant register'!$A:$A,0))<>"",IF(F26="Due diligence",INDEX('Grant register'!$K:$K,MATCH($A26,'Grant register'!$A:$A,0))<>"",IF(F26="Interim report",INDEX('Grant register'!$O:$O,MATCH($A26,'Grant register'!$A:$A,0))<>"",IF(F26="Final report",INDEX('Grant register'!$Q:$Q,MATCH($A26,'Grant register'!$A:$A,0))<>"",IF(F26="Evidence",INDEX('Grant register'!$S:$S,MATCH($A26,'Grant register'!$A:$A,0))="Received",IF(F26="Condition",INDEX('Grant register'!$M:$M,MATCH($A26,'Grant register'!$A:$A,0))="Yes",IF(F26="Interim report + evidence",AND(INDEX('Grant register'!$O:$O,MATCH($A26,'Grant register'!$A:$A,0))<>"",INDEX('Grant register'!$S:$S,MATCH($A26,'Grant register'!$A:$A,0))="Received"),FALSE))))))))) -> TRUE | H26: OK | I26: yes | J26: =IF($A26="","",IF(I26<>"","Paid",IF(H26="Verify","Blocked: verify bank details",IF(E26="","Due date missing",IF(G26,IF(E26<=TODAY()+30,"Ready for approval","Scheduled"),IF(E26<=TODAY()+30,"Blocked: waiting for "&LOWER(F26),"Waiting: "&LOWER(F26))))))) -> Paid | K26: =IF(OR($A26="",I26<>"",E26="",E26>=TODAY()),"",TODAY()-E26)
A27: CF-2025-021 | B27: Oakfield Carers Network | C27: 1 | D27: 10000 | E27: 45931 | F27: Agreement | G27: =IF($A27="","",IF(OR(F27="None",F27=""),TRUE,IF(F27="Agreement",INDEX('Grant register'!$J:$J,MATCH($A27,'Grant register'!$A:$A,0))<>"",IF(F27="Due diligence",INDEX('Grant register'!$K:$K,MATCH($A27,'Grant register'!$A:$A,0))<>"",IF(F27="Interim report",INDEX('Grant register'!$O:$O,MATCH($A27,'Grant register'!$A:$A,0))<>"",IF(F27="Final report",INDEX('Grant register'!$Q:$Q,MATCH($A27,'Grant register'!$A:$A,0))<>"",IF(F27="Evidence",INDEX('Grant register'!$S:$S,MATCH($A27,'Grant register'!$A:$A,0))="Received",IF(F27="Condition",INDEX('Grant register'!$M:$M,MATCH($A27,'Grant register'!$A:$A,0))="Yes",IF(F27="Interim report + evidence",AND(INDEX('Grant register'!$O:$O,MATCH($A27,'Grant register'!$A:$A,0))<>"",INDEX('Grant register'!$S:$S,MATCH($A27,'Grant register'!$A:$A,0))="Received"),FALSE))))))))) -> TRUE | H27: OK | I27: yes | J27: =IF($A27="","",IF(I27<>"","Paid",IF(H27="Verify","Blocked: verify bank details",IF(E27="","Due date missing",IF(G27,IF(E27<=TODAY()+30,"Ready for approval","Scheduled"),IF(E27<=TODAY()+30,"Blocked: waiting for "&LOWER(F27),"Waiting: "&LOWER(F27))))))) -> Paid | K27: =IF(OR($A27="",I27<>"",E27="",E27>=TODAY()),"",TODAY()-E27)
A28: CF-2025-021 | B28: Oakfield Carers Network | C28: 2 | D28: 10000 | E28: 46113 | F28: Interim report | G28: =IF($A28="","",IF(OR(F28="None",F28=""),TRUE,IF(F28="Agreement",INDEX('Grant register'!$J:$J,MATCH($A28,'Grant register'!$A:$A,0))<>"",IF(F28="Due diligence",INDEX('Grant register'!$K:$K,MATCH($A28,'Grant register'!$A:$A,0))<>"",IF(F28="Interim report",INDEX('Grant register'!$O:$O,MATCH($A28,'Grant register'!$A:$A,0))<>"",IF(F28="Final report",INDEX('Grant register'!$Q:$Q,MATCH($A28,'Grant register'!$A:$A,0))<>"",IF(F28="Evidence",INDEX('Grant register'!$S:$S,MATCH($A28,'Grant register'!$A:$A,0))="Received",IF(F28="Condition",INDEX('Grant register'!$M:$M,MATCH($A28,'Grant register'!$A:$A,0))="Yes",IF(F28="Interim report + evidence",AND(INDEX('Grant register'!$O:$O,MATCH($A28,'Grant register'!$A:$A,0))<>"",INDEX('Grant register'!$S:$S,MATCH($A28,'Grant register'!$A:$A,0))="Received"),FALSE))))))))) -> TRUE | H28: OK | I28: yes | J28: =IF($A28="","",IF(I28<>"","Paid",IF(H28="Verify","Blocked: verify bank details",IF(E28="","Due date missing",IF(G28,IF(E28<=TODAY()+30,"Ready for approval","Scheduled"),IF(E28<=TODAY()+30,"Blocked: waiting for "&LOWER(F28),"Waiting: "&LOWER(F28))))))) -> Paid | K28: =IF(OR($A28="",I28<>"",E28="",E28>=TODAY()),"",TODAY()-E28)
A29: CF-2025-022 | B29: Northbridge Men's Shed | C29: 1 | D29: 6000 | E29: 45931 | F29: Agreement | G29: =IF($A29="","",IF(OR(F29="None",F29=""),TRUE,IF(F29="Agreement",INDEX('Grant register'!$J:$J,MATCH($A29,'Grant register'!$A:$A,0))<>"",IF(F29="Due diligence",INDEX('Grant register'!$K:$K,MATCH($A29,'Grant register'!$A:$A,0))<>"",IF(F29="Interim report",INDEX('Grant register'!$O:$O,MATCH($A29,'Grant register'!$A:$A,0))<>"",IF(F29="Final report",INDEX('Grant register'!$Q:$Q,MATCH($A29,'Grant register'!$A:$A,0))<>"",IF(F29="Evidence",INDEX('Grant register'!$S:$S,MATCH($A29,'Grant register'!$A:$A,0))="Received",IF(F29="Condition",INDEX('Grant register'!$M:$M,MATCH($A29,'Grant register'!$A:$A,0))="Yes",IF(F29="Interim report + evidence",AND(INDEX('Grant register'!$O:$O,MATCH($A29,'Grant register'!$A:$A,0))<>"",INDEX('Grant register'!$S:$S,MATCH($A29,'Grant register'!$A:$A,0))="Received"),FALSE))))))))) -> TRUE | H29: OK | I29: yes | J29: =IF($A29="","",IF(I29<>"","Paid",IF(H29="Verify","Blocked: verify bank details",IF(E29="","Due date missing",IF(G29,IF(E29<=TODAY()+30,"Ready for approval","Scheduled"),IF(E29<=TODAY()+30,"Blocked: waiting for "&LOWER(F29),"Waiting: "&LOWER(F29))))))) -> Paid | K29: =IF(OR($A29="",I29<>"",E29="",E29>=TODAY()),"",TODAY()-E29)
A30: YM25/09 | B30: Rhythm & Roots Drumming | C30: 1 | D30: 3600 | E30: 45940 | F30: Agreement | G30: =IF($A30="","",IF(OR(F30="None",F30=""),TRUE,IF(F30="Agreement",INDEX('Grant register'!$J:$J,MATCH($A30,'Grant register'!$A:$A,0))<>"",IF(F30="Due diligence",INDEX('Grant register'!$K:$K,MATCH($A30,'Grant register'!$A:$A,0))<>"",IF(F30="Interim report",INDEX('Grant register'!$O:$O,MATCH($A30,'Grant register'!$A:$A,0))<>"",IF(F30="Final report",INDEX('Grant register'!$Q:$Q,MATCH($A30,'Grant register'!$A:$A,0))<>"",IF(F30="Evidence",INDEX('Grant register'!$S:$S,MATCH($A30,'Grant register'!$A:$A,0))="Received",IF(F30="Condition",INDEX('Grant register'!$M:$M,MATCH($A30,'Grant register'!$A:$A,0))="Yes",IF(F30="Interim report + evidence",AND(INDEX('Grant register'!$O:$O,MATCH($A30,'Grant register'!$A:$A,0))<>"",INDEX('Grant register'!$S:$S,MATCH($A30,'Grant register'!$A:$A,0))="Received"),FALSE))))))))) -> TRUE | H30: OK | I30: yes | J30: =IF($A30="","",IF(I30<>"","Paid",IF(H30="Verify","Blocked: verify bank details",IF(E30="","Due date missing",IF(G30,IF(E30<=TODAY()+30,"Ready for approval","Scheduled"),IF(E30<=TODAY()+30,"Blocked: waiting for "&LOWER(F30),"Waiting: "&LOWER(F30))))))) -> Paid | K30: =IF(OR($A30="",I30<>"",E30="",E30>=TODAY()),"",TODAY()-E30)
A31: YM25/09 | B31: Rhythm & Roots Drumming | C31: 2 | D31: 3600 | E31: 46152 | F31: Interim report | G31: =IF($A31="","",IF(OR(F31="None",F31=""),TRUE,IF(F31="Agreement",INDEX('Grant register'!$J:$J,MATCH($A31,'Grant register'!$A:$A,0))<>"",IF(F31="Due diligence",INDEX('Grant register'!$K:$K,MATCH($A31,'Grant register'!$A:$A,0))<>"",IF(F31="Interim report",INDEX('Grant register'!$O:$O,MATCH($A31,'Grant register'!$A:$A,0))<>"",IF(F31="Final report",INDEX('Grant register'!$Q:$Q,MATCH($A31,'Grant register'!$A:$A,0))<>"",IF(F31="Evidence",INDEX('Grant register'!$S:$S,MATCH($A31,'Grant register'!$A:$A,0))="Received",IF(F31="Condition",INDEX('Grant register'!$M:$M,MATCH($A31,'Grant register'!$A:$A,0))="Yes",IF(F31="Interim report + evidence",AND(INDEX('Grant register'!$O:$O,MATCH($A31,'Grant register'!$A:$A,0))<>"",INDEX('Grant register'!$S:$S,MATCH($A31,'Grant register'!$A:$A,0))="Received"),FALSE))))))))) -> FALSE | H31: OK | J31: =IF($A31="","",IF(I31<>"","Paid",IF(H31="Verify","Blocked: verify bank details",IF(E31="","Due date missing",IF(G31,IF(E31<=TODAY()+30,"Ready for approval","Scheduled"),IF(E31<=TODAY()+30,"Blocked: waiting for "&LOWER(F31),"Waiting: "&LOWER(F31))))))) -> Blocked: waiting for interim report | K31: =IF(OR($A31="",I31<>"",E31="",E31>=TODAY()),"",TODAY()-E31) -> 141
A32: CAP-10 | B32: Eastfield Village Hall | C32: 1 | D32: 3500 | E32: 46310 | F32: Evidence | G32: =IF($A32="","",IF(OR(F32="None",F32=""),TRUE,IF(F32="Agreement",INDEX('Grant register'!$J:$J,MATCH($A32,'Grant register'!$A:$A,0))<>"",IF(F32="Due diligence",INDEX('Grant register'!$K:$K,MATCH($A32,'Grant register'!$A:$A,0))<>"",IF(F32="Interim report",INDEX('Grant register'!$O:$O,MATCH($A32,'Grant register'!$A:$A,0))<>"",IF(F32="Final report",INDEX('Grant register'!$Q:$Q,MATCH($A32,'Grant register'!$A:$A,0))<>"",IF(F32="Evidence",INDEX('Grant register'!$S:$S,MATCH($A32,'Grant register'!$A:$A,0))="Received",IF(F32="Condition",INDEX('Grant register'!$M:$M,MATCH($A32,'Grant register'!$A:$A,0))="Yes",IF(F32="Interim report + evidence",AND(INDEX('Grant register'!$O:$O,MATCH($A32,'Grant register'!$A:$A,0))<>"",INDEX('Grant register'!$S:$S,MATCH($A32,'Grant register'!$A:$A,0))="Received"),FALSE))))))))) -> TRUE | H32: Verify | J32: =IF($A32="","",IF(I32<>"","Paid",IF(H32="Verify","Blocked: verify bank details",IF(E32="","Due date missing",IF(G32,IF(E32<=TODAY()+30,"Ready for approval","Scheduled"),IF(E32<=TODAY()+30,"Blocked: waiting for "&LOWER(F32),"Waiting: "&LOWER(F32))))))) -> Blocked: verify bank details | K32: =IF(OR($A32="",I32<>"",E32="",E32>=TODAY()),"",TODAY()-E32)

Sheet Grant register
A1: Grant ref | B1: Recipient | C1: Reg. no. | D1: Fund | E1: Owner | F1: Awarded £ | G1: Paid to date £ | H1: Award date | I1: End date | J1: Agreement signed | K1: DD last checked | L1: Conditions | M1: Conditions met? | N1: Interim report due | O1: Interim received | P1: Final report due | Q1: Final received | R1: Evidence required | S1: Evidence status | T1: Report status | U1: Payments | V1: Checks | W1: Needs attention? | X1: Notes
A2: CF-2025-014 | B2: Harbour Youth Project CIO | C2: 1181234 | D2: Community Fund | E2: Sarah J | F2: 25000 | G2: =SUMIFS(Payments!$D:$D,Payments!$A:$A,$A2,Payments!$I:$I,"<>") -> 15000 | H2: 46204 | I2: 46568 | J2: yes | K2: 46205 | L2: Restricted to youth skills delivery | M2: Yes | N2: 46309 | P2: 46599 | R2: receipts for tranche 1 spend - not yet | S2: Missing | T2: =IF($A2="","",IF(AND(N2<>"",O2="",N2<TODAY()),"Interim overdue "&(TODAY()-N2)&"d",IF(AND(P2<>"",Q2="",P2<TODAY()),"Final overdue "&(TODAY()-P2)&"d",IF(AND(N2<>"",O2="",N2-TODAY()<=30),"Interim due in "&(N2-TODAY())&"d",IF(AND(P2<>"",Q2="",P2-TODAY()<=30),"Final due in "&(P2-TODAY())&"d","OK"))))) -> Interim due in 16d | U2: =IF($A2="","",IF(COUNTIFS(Payments!$A:$A,$A2,Payments!$J:$J,"Blocked*")>0,"Payment blocked",IF(COUNTIFS(Payments!$A:$A,$A2,Payments!$J:$J,"Ready*")>0,"Payment ready",""))) -> Payment blocked | V2: =IF($A2="","",IF(K2="","No DD date; ",IF(ISNUMBER(K2),IF(TODAY()-K2>365,"DD over 12 months; ",""),"DD date unknown; "))&IF(J2="","No agreement; ","")&IF(M2="No","Condition open; ","")&IF(OR(S2="Missing",S2="Partial"),"Evidence "&LOWER(S2)&"; ","")) -> Evidence missing; | W2: =IF($A2="","",IF(OR(T2<>"OK",U2<>"",V2<>""),"Yes","No")) -> Yes | X2: chased for receipts 16/9
A3: CF-2025-009 | B3: Harbour Youth Proj. | D3: Community Fund | E3: Sarah J | F3: 5000 | G3: =SUMIFS(Payments!$D:$D,Payments!$A:$A,$A3,Payments!$I:$I,"<>") -> 5000 | H3: 45964 | I3: 46265 | J3: yes | K3: yes | P3: 46295 | T3: =IF($A3="","",IF(AND(N3<>"",O3="",N3<TODAY()),"Interim overdue "&(TODAY()-N3)&"d",IF(AND(P3<>"",Q3="",P3<TODAY()),"Final overdue "&(TODAY()-P3)&"d",IF(AND(N3<>"",O3="",N3-TODAY()<=30),"Interim due in "&(N3-TODAY())&"d",IF(AND(P3<>"",Q3="",P3-TODAY()<=30),"Final due in "&(P3-TODAY())&"d","OK"))))) -> Final due in 2d | U3: =IF($A3="","",IF(COUNTIFS(Payments!$A:$A,$A3,Payments!$J:$J,"Blocked*")>0,"Payment blocked",IF(COUNTIFS(Payments!$A:$A,$A3,Payments!$J:$J,"Ready*")>0,"Payment ready",""))) | V3: =IF($A3="","",IF(K3="","No DD date; ",IF(ISNUMBER(K3),IF(TODAY()-K3>365,"DD over 12 months; ",""),"DD date unknown; "))&IF(J3="","No agreement; ","")&IF(M3="No","Condition open; ","")&IF(OR(S3="Missing",S3="Partial"),"Evidence "&LOWER(S3)&"; ","")) -> DD date unknown; | W3: =IF($A3="","",IF(OR(T3<>"OK",U3<>"",V3<>""),"Yes","No")) -> Yes
A4: YM25/03 | B4: Northgate Music Collective | C4: 1190001 | D4: Youth Music | E4: Tom B | F4: 12500 | G4: =SUMIFS(Payments!$D:$D,Payments!$A:$A,$A4,Payments!$I:$I,"<>") -> 6250 | H4: 46037 | I4: 46387 | J4: yes | K4: 45667 | L4: DBS checks for tutors confirmed before term 2 | M4: No | N4: 46234 | P4: 46387 | T4: =IF($A4="","",IF(AND(N4<>"",O4="",N4<TODAY()),"Interim overdue "&(TODAY()-N4)&"d",IF(AND(P4<>"",Q4="",P4<TODAY()),"Final overdue "&(TODAY()-P4)&"d",IF(AND(N4<>"",O4="",N4-TODAY()<=30),"Interim due in "&(N4-TODAY())&"d",IF(AND(P4<>"",Q4="",P4-TODAY()<=30),"Final due in "&(P4-TODAY())&"d","OK"))))) -> Interim overdue 59d | U4: =IF($A4="","",IF(COUNTIFS(Payments!$A:$A,$A4,Payments!$J:$J,"Blocked*")>0,"Payment blocked",IF(COUNTIFS(Payments!$A:$A,$A4,Payments!$J:$J,"Ready*")>0,"Payment ready",""))) -> Payment blocked | V4: =IF($A4="","",IF(K4="","No DD date; ",IF(ISNUMBER(K4),IF(TODAY()-K4>365,"DD over 12 months; ",""),"DD date unknown; "))&IF(J4="","No agreement; ","")&IF(M4="No","Condition open; ","")&IF(OR(S4="Missing",S4="Partial"),"Evidence "&LOWER(S4)&"; ","")) -> DD over 12 months; Condition open; | W4: =IF($A4="","",IF(OR(T4<>"OK",U4<>"",V4<>""),"Yes","No")) -> Yes | X4: chased 2x, new coordinator started Aug
A5: YM25/05 | B5: St Anne's Community Choir | D5: Youth Music | E5: Tom B | F5: 3000 | G5: =SUMIFS(Payments!$D:$D,Payments!$A:$A,$A5,Payments!$I:$I,"<>") -> 3000 | H5: 46086 | I5: 46446 | P5: 46477 | T5: =IF($A5="","",IF(AND(N5<>"",O5="",N5<TODAY()),"Interim overdue "&(TODAY()-N5)&"d",IF(AND(P5<>"",Q5="",P5<TODAY()),"Final overdue "&(TODAY()-P5)&"d",IF(AND(N5<>"",O5="",N5-TODAY()<=30),"Interim due in "&(N5-TODAY())&"d",IF(AND(P5<>"",Q5="",P5-TODAY()<=30),"Final due in "&(P5-TODAY())&"d","OK"))))) -> OK | U5: =IF($A5="","",IF(COUNTIFS(Payments!$A:$A,$A5,Payments!$J:$J,"Blocked*")>0,"Payment blocked",IF(COUNTIFS(Payments!$A:$A,$A5,Payments!$J:$J,"Ready*")>0,"Payment ready",""))) | V5: =IF($A5="","",IF(K5="","No DD date; ",IF(ISNUMBER(K5),IF(TODAY()-K5>365,"DD over 12 months; ",""),"DD date unknown; "))&IF(J5="","No agreement; ","")&IF(M5="No","Condition open; ","")&IF(OR(S5="Missing",S5="Partial"),"Evidence "&LOWER(S5)&"; ","")) -> No DD date; No agreement; | W5: =IF($A5="","",IF(OR(T5<>"OK",U5<>"",V5<>""),"Yes","No")) -> Yes | X5: paid before agreement returned?? check
A6: CAP-7 | B6: Riverside Scout Group | C6: 1100456 | D6: Capital Grants | E6: Priya K | F6: 40000 | G6: =SUMIFS(Payments!$D:$D,Payments!$A:$A,$A6,Payments!$I:$I,"<>") -> 20000 | H6: 46023 | I6: 46477 | J6: 46034 | K6: 46003 | L6: Planning permission evidence before tranche 3 | M6: No | N6: 46203 | O6: 46205 | P6: 46477 | R6: contractor invoices - some received | S6: Partial | T6: =IF($A6="","",IF(AND(N6<>"",O6="",N6<TODAY()),"Interim overdue "&(TODAY()-N6)&"d",IF(AND(P6<>"",Q6="",P6<TODAY()),"Final overdue "&(TODAY()-P6)&"d",IF(AND(N6<>"",O6="",N6-TODAY()<=30),"Interim due in "&(N6-TODAY())&"d",IF(AND(P6<>"",Q6="",P6-TODAY()<=30),"Final due in "&(P6-TODAY())&"d","OK"))))) -> OK | U6: =IF($A6="","",IF(COUNTIFS(Payments!$A:$A,$A6,Payments!$J:$J,"Blocked*")>0,"Payment blocked",IF(COUNTIFS(Payments!$A:$A,$A6,Payments!$J:$J,"Ready*")>0,"Payment ready",""))) -> Payment blocked | V6: =IF($A6="","",IF(K6="","No DD date; ",IF(ISNUMBER(K6),IF(TODAY()-K6>365,"DD over 12 months; ",""),"DD date unknown; "))&IF(J6="","No agreement; ","")&IF(M6="No","Condition open; ","")&IF(OR(S6="Missing",S6="Partial"),"Evidence "&LOWER(S6)&"; ","")) -> Condition open; Evidence partial; | W6: =IF($A6="","",IF(OR(T6<>"OK",U6<>"",V6<>""),"Yes","No")) -> Yes
A7: CAP-8 | B7: Eastfield Village Hall | C7: 1123456 | D7: Capital Grants | E7: Priya K | F7: 18000 | G7: =SUMIFS(Payments!$D:$D,Payments!$A:$A,$A7,Payments!$I:$I,"<>") -> 9000 | H7: 46073 | I7: 46387 | J7: yes | K7: 46071 | P7: 46326 | R7: completion certificate + photos | S7: Missing | T7: =IF($A7="","",IF(AND(N7<>"",O7="",N7<TODAY()),"Interim overdue "&(TODAY()-N7)&"d",IF(AND(P7<>"",Q7="",P7<TODAY()),"Final overdue "&(TODAY()-P7)&"d",IF(AND(N7<>"",O7="",N7-TODAY()<=30),"Interim due in "&(N7-TODAY())&"d",IF(AND(P7<>"",Q7="",P7-TODAY()<=30),"Final due in "&(P7-TODAY())&"d","OK"))))) -> OK | U7: =IF($A7="","",IF(COUNTIFS(Payments!$A:$A,$A7,Payments!$J:$J,"Blocked*")>0,"Payment blocked",IF(COUNTIFS(Payments!$A:$A,$A7,Payments!$J:$J,"Ready*")>0,"Payment ready",""))) -> Payment blocked | V7: =IF($A7="","",IF(K7="","No DD date; ",IF(ISNUMBER(K7),IF(TODAY()-K7>365,"DD over 12 months; ",""),"DD date unknown; "))&IF(J7="","No agreement; ","")&IF(M7="No","Condition open; ","")&IF(OR(S7="Missing",S7="Partial"),"Evidence "&LOWER(S7)&"; ","")) -> Evidence missing; | W7: =IF($A7="","",IF(OR(T7<>"OK",U7<>"",V7<>""),"Yes","No")) -> Yes | X7: bank details changed - verify before next payment!
A8: HF-101 | B8: Mercy Street Food Bank | C8: 1170777 | D8: Hardship Fund | E8: Sarah J | F8: 2500 | G8: =SUMIFS(Payments!$D:$D,Payments!$A:$A,$A8,Payments!$I:$I,"<>") -> 2500 | H8: 46266 | I8: 46387 | J8: yes | K8: 46254 | P8: 46418 | T8: =IF($A8="","",IF(AND(N8<>"",O8="",N8<TODAY()),"Interim overdue "&(TODAY()-N8)&"d",IF(AND(P8<>"",Q8="",P8<TODAY()),"Final overdue "&(TODAY()-P8)&"d",IF(AND(N8<>"",O8="",N8-TODAY()<=30),"Interim due in "&(N8-TODAY())&"d",IF(AND(P8<>"",Q8="",P8-TODAY()<=30),"Final due in "&(P8-TODAY())&"d","OK"))))) -> OK | U8: =IF($A8="","",IF(COUNTIFS(Payments!$A:$A,$A8,Payments!$J:$J,"Blocked*")>0,"Payment blocked",IF(COUNTIFS(Payments!$A:$A,$A8,Payments!$J:$J,"Ready*")>0,"Payment ready",""))) | V8: =IF($A8="","",IF(K8="","No DD date; ",IF(ISNUMBER(K8),IF(TODAY()-K8>365,"DD over 12 months; ",""),"DD date unknown; "))&IF(J8="","No agreement; ","")&IF(M8="No","Condition open; ","")&IF(OR(S8="Missing",S8="Partial"),"Evidence "&LOWER(S8)&"; ","")) | W8: =IF($A8="","",IF(OR(T8<>"OK",U8<>"",V8<>""),"Yes","No")) -> No
A9: HF-102 | B9: Mercy Street Food Bank | C9: 1170777 | D9: Hardship Fund | E9: Sarah J | F9: 1500 | G9: =SUMIFS(Payments!$D:$D,Payments!$A:$A,$A9,Payments!$I:$I,"<>") -> 0 | H9: 46277 | I9: 46387 | K9: 46254 | P9: 46418 | T9: =IF($A9="","",IF(AND(N9<>"",O9="",N9<TODAY()),"Interim overdue "&(TODAY()-N9)&"d",IF(AND(P9<>"",Q9="",P9<TODAY()),"Final overdue "&(TODAY()-P9)&"d",IF(AND(N9<>"",O9="",N9-TODAY()<=30),"Interim due in "&(N9-TODAY())&"d",IF(AND(P9<>"",Q9="",P9-TODAY()<=30),"Final due in "&(P9-TODAY())&"d","OK"))))) -> OK | U9: =IF($A9="","",IF(COUNTIFS(Payments!$A:$A,$A9,Payments!$J:$J,"Blocked*")>0,"Payment blocked",IF(COUNTIFS(Payments!$A:$A,$A9,Payments!$J:$J,"Ready*")>0,"Payment ready",""))) -> Payment blocked | V9: =IF($A9="","",IF(K9="","No DD date; ",IF(ISNUMBER(K9),IF(TODAY()-K9>365,"DD over 12 months; ",""),"DD date unknown; "))&IF(J9="","No agreement; ","")&IF(M9="No","Condition open; ","")&IF(OR(S9="Missing",S9="Partial"),"Evidence "&LOWER(S9)&"; ","")) -> No agreement; | W9: =IF($A9="","",IF(OR(T9<>"OK",U9<>"",V9<>""),"Yes","No")) -> Yes
A10: CF-2026-002 | B10: Lanterns Mental Health Peer Support | C10: 1201122 | D10: Community Fund | E10: Sarah J | F10: 30000 | G10: =SUMIFS(Payments!$D:$D,Payments!$A:$A,$A10,Payments!$I:$I,"<>") -> 15000 | H10: 46063 | I10: 46427 | J10: yes | K10: 46054 | N10: 46244 | O10: 46239 | P10: 46455 | T10: =IF($A10="","",IF(AND(N10<>"",O10="",N10<TODAY()),"Interim overdue "&(TODAY()-N10)&"d",IF(AND(P10<>"",Q10="",P10<TODAY()),"Final overdue "&(TODAY()-P10)&"d",IF(AND(N10<>"",O10="",N10-TODAY()<=30),"Interim due in "&(N10-TODAY())&"d",IF(AND(P10<>"",Q10="",P10-TODAY()<=30),"Final due in "&(P10-TODAY())&"d","OK"))))) -> OK | U10: =IF($A10="","",IF(COUNTIFS(Payments!$A:$A,$A10,Payments!$J:$J,"Blocked*")>0,"Payment blocked",IF(COUNTIFS(Payments!$A:$A,$A10,Payments!$J:$J,"Ready*")>0,"Payment ready",""))) -> Payment ready | V10: =IF($A10="","",IF(K10="","No DD date; ",IF(ISNUMBER(K10),IF(TODAY()-K10>365,"DD over 12 months; ",""),"DD date unknown; "))&IF(J10="","No agreement; ","")&IF(M10="No","Condition open; ","")&IF(OR(S10="Missing",S10="Partial"),"Evidence "&LOWER(S10)&"; ","")) | W10: =IF($A10="","",IF(OR(T10<>"OK",U10<>"",V10<>""),"Yes","No")) -> Yes | X10: interim report fine - T2 to go to Oct trustees?
A11: CF-2026-005 | B11: Greenway Allotment Society | D11: Community Fund | F11: 4000 | G11: =SUMIFS(Payments!$D:$D,Payments!$A:$A,$A11,Payments!$I:$I,"<>") -> 4000 | H11: 46115 | I11: 46265 | J11: yes | K11: 46113 | P11: 46266 | R11: photos of new raised beds | S11: Missing | T11: =IF($A11="","",IF(AND(N11<>"",O11="",N11<TODAY()),"Interim overdue "&(TODAY()-N11)&"d",IF(AND(P11<>"",Q11="",P11<TODAY()),"Final overdue "&(TODAY()-P11)&"d",IF(AND(N11<>"",O11="",N11-TODAY()<=30),"Interim due in "&(N11-TODAY())&"d",IF(AND(P11<>"",Q11="",P11-TODAY()<=30),"Final due in "&(P11-TODAY())&"d","OK"))))) -> Final overdue 27d | U11: =IF($A11="","",IF(COUNTIFS(Payments!$A:$A,$A11,Payments!$J:$J,"Blocked*")>0,"Payment blocked",IF(COUNTIFS(Payments!$A:$A,$A11,Payments!$J:$J,"Ready*")>0,"Payment ready",""))) | V11: =IF($A11="","",IF(K11="","No DD date; ",IF(ISNUMBER(K11),IF(TODAY()-K11>365,"DD over 12 months; ",""),"DD date unknown; "))&IF(J11="","No agreement; ","")&IF(M11="No","Condition open; ","")&IF(OR(S11="Missing",S11="Partial"),"Evidence "&LOWER(S11)&"; ","")) -> Evidence missing; | W11: =IF($A11="","",IF(OR(T11<>"OK",U11<>"",V11<>""),"Yes","No")) -> Yes
A12: CF-2026-007 | B12: Kids Code Club Northbridge | C12: 1195555 | D12: Community Fund | E12: Tom B | F12: 8000 | G12: =SUMIFS(Payments!$D:$D,Payments!$A:$A,$A12,Payments!$I:$I,"<>") -> 4000 | H12: 46143 | I12: 46507 | J12: yes | K12: 46140 | N12: 46327 | P12: 46507 | T12: =IF($A12="","",IF(AND(N12<>"",O12="",N12<TODAY()),"Interim overdue "&(TODAY()-N12)&"d",IF(AND(P12<>"",Q12="",P12<TODAY()),"Final overdue "&(TODAY()-P12)&"d",IF(AND(N12<>"",O12="",N12-TODAY()<=30),"Interim due in "&(N12-TODAY())&"d",IF(AND(P12<>"",Q12="",P12-TODAY()<=30),"Final due in "&(P12-TODAY())&"d","OK"))))) -> OK | U12: =IF($A12="","",IF(COUNTIFS(Payments!$A:$A,$A12,Payments!$J:$J,"Blocked*")>0,"Payment blocked",IF(COUNTIFS(Payments!$A:$A,$A12,Payments!$J:$J,"Ready*")>0,"Payment ready",""))) | V12: =IF($A12="","",IF(K12="","No DD date; ",IF(ISNUMBER(K12),IF(TODAY()-K12>365,"DD over 12 months; ",""),"DD date unknown; "))&IF(J12="","No agreement; ","")&IF(M12="No","Condition open; ","")&IF(OR(S12="Missing",S12="Partial"),"Evidence "&LOWER(S12)&"; ","")) | W12: =IF($A12="","",IF(OR(T12<>"OK",U12<>"",V12<>""),"Yes","No")) -> No
A13: YM26/01 | B13: Brass for All | C13: 1150333 | D13: Youth Music | E13: Tom B | F13: 15000 | G13: =SUMIFS(Payments!$D:$D,Payments!$A:$A,$A13,Payments!$I:$I,"<>") -> 5000 | H13: 46174 | I13: 46538 | J13: yes | K13: 46172 | L13: Spring termly report by 15/01/2027 before the February payment | M13: No | N13: 46280 | P13: 46538 | T13: =IF($A13="","",IF(AND(N13<>"",O13="",N13<TODAY()),"Interim overdue "&(TODAY()-N13)&"d",IF(AND(P13<>"",Q13="",P13<TODAY()),"Final overdue "&(TODAY()-P13)&"d",IF(AND(N13<>"",O13="",N13-TODAY()<=30),"Interim due in "&(N13-TODAY())&"d",IF(AND(P13<>"",Q13="",P13-TODAY()<=30),"Final due in "&(P13-TODAY())&"d","OK"))))) -> Interim overdue 13d | U13: =IF($A13="","",IF(COUNTIFS(Payments!$A:$A,$A13,Payments!$J:$J,"Blocked*")>0,"Payment blocked",IF(COUNTIFS(Payments!$A:$A,$A13,Payments!$J:$J,"Ready*")>0,"Payment ready",""))) -> Payment blocked | V13: =IF($A13="","",IF(K13="","No DD date; ",IF(ISNUMBER(K13),IF(TODAY()-K13>365,"DD over 12 months; ",""),"DD date unknown; "))&IF(J13="","No agreement; ","")&IF(M13="No","Condition open; ","")&IF(OR(S13="Missing",S13="Partial"),"Evidence "&LOWER(S13)&"; ","")) -> Condition open; | W13: =IF($A13="","",IF(OR(T13<>"OK",U13<>"",V13<>""),"Yes","No")) -> Yes
A14: YM26/02 | B14: The Beat Box Studio CIC | C14: CIC12345678 | D14: Youth Music | E14: Tom B | F14: 9500 | G14: =SUMIFS(Payments!$D:$D,Payments!$A:$A,$A14,Payments!$I:$I,"<>") -> 9500 | H14: 46193 | I14: 46568 | J14: yes | K14: 46191 | L14: Safeguarding policy to be provided within 3 months (by 20/09/2026) | M14: No | P14: 46568 | T14: =IF($A14="","",IF(AND(N14<>"",O14="",N14<TODAY()),"Interim overdue "&(TODAY()-N14)&"d",IF(AND(P14<>"",Q14="",P14<TODAY()),"Final overdue "&(TODAY()-P14)&"d",IF(AND(N14<>"",O14="",N14-TODAY()<=30),"Interim due in "&(N14-TODAY())&"d",IF(AND(P14<>"",Q14="",P14-TODAY()<=30),"Final due in "&(P14-TODAY())&"d","OK"))))) -> OK | U14: =IF($A14="","",IF(COUNTIFS(Payments!$A:$A,$A14,Payments!$J:$J,"Blocked*")>0,"Payment blocked",IF(COUNTIFS(Payments!$A:$A,$A14,Payments!$J:$J,"Ready*")>0,"Payment ready",""))) | V14: =IF($A14="","",IF(K14="","No DD date; ",IF(ISNUMBER(K14),IF(TODAY()-K14>365,"DD over 12 months; ",""),"DD date unknown; "))&IF(J14="","No agreement; ","")&IF(M14="No","Condition open; ","")&IF(OR(S14="Missing",S14="Partial"),"Evidence "&LOWER(S14)&"; ","")) -> Condition open; | W14: =IF($A14="","",IF(OR(T14<>"OK",U14<>"",V14<>""),"Yes","No")) -> Yes
A15: CAP-9 | B15: Hilltop Community Cafe | C15: 1188888 | D15: Capital Grants | E15: Priya K | F15: 22000 | G15: =SUMIFS(Payments!$D:$D,Payments!$A:$A,$A15,Payments!$I:$I,"<>") -> 22000 | H15: 46003 | I15: 46203 | J15: yes | K15: 46001 | P15: 46203 | Q15: 46201 | R15: invoices received | S15: Received | T15: =IF($A15="","",IF(AND(N15<>"",O15="",N15<TODAY()),"Interim overdue "&(TODAY()-N15)&"d",IF(AND(P15<>"",Q15="",P15<TODAY()),"Final overdue "&(TODAY()-P15)&"d",IF(AND(N15<>"",O15="",N15-TODAY()<=30),"Interim due in "&(N15-TODAY())&"d",IF(AND(P15<>"",Q15="",P15-TODAY()<=30),"Final due in "&(P15-TODAY())&"d","OK"))))) -> OK | U15: =IF($A15="","",IF(COUNTIFS(Payments!$A:$A,$A15,Payments!$J:$J,"Blocked*")>0,"Payment blocked",IF(COUNTIFS(Payments!$A:$A,$A15,Payments!$J:$J,"Ready*")>0,"Payment ready",""))) | V15: =IF($A15="","",IF(K15="","No DD date; ",IF(ISNUMBER(K15),IF(TODAY()-K15>365,"DD over 12 months; ",""),"DD date unknown; "))&IF(J15="","No agreement; ","")&IF(M15="No","Condition open; ","")&IF(OR(S15="Missing",S15="Partial"),"Evidence "&LOWER(S15)&"; ","")) | W15: =IF($A15="","",IF(OR(T15<>"OK",U15<>"",V15<>""),"Yes","No")) -> No | X15: all done?
A16: HF-103 | B16: Westside Refugee Welcome | C16: 1177777 | D16: Hardship Fund | E16: Sarah J | F16: 3000 | G16: =SUMIFS(Payments!$D:$D,Payments!$A:$A,$A16,Payments!$I:$I,"<>") -> 3000 | H16: 46280 | I16: 46477 | J16: yes | P16: 46507 | T16: =IF($A16="","",IF(AND(N16<>"",O16="",N16<TODAY()),"Interim overdue "&(TODAY()-N16)&"d",IF(AND(P16<>"",Q16="",P16<TODAY()),"Final overdue "&(TODAY()-P16)&"d",IF(AND(N16<>"",O16="",N16-TODAY()<=30),"Interim due in "&(N16-TODAY())&"d",IF(AND(P16<>"",Q16="",P16-TODAY()<=30),"Final due in "&(P16-TODAY())&"d","OK"))))) -> OK | U16: =IF($A16="","",IF(COUNTIFS(Payments!$A:$A,$A16,Payments!$J:$J,"Blocked*")>0,"Payment blocked",IF(COUNTIFS(Payments!$A:$A,$A16,Payments!$J:$J,"Ready*")>0,"Payment ready",""))) | V16: =IF($A16="","",IF(K16="","No DD date; ",IF(ISNUMBER(K16),IF(TODAY()-K16>365,"DD over 12 months; ",""),"DD date unknown; "))&IF(J16="","No agreement; ","")&IF(M16="No","Condition open; ","")&IF(OR(S16="Missing",S16="Partial"),"Evidence "&LOWER(S16)&"; ","")) -> No DD date; | W16: =IF($A16="","",IF(OR(T16<>"OK",U16<>"",V16<>""),"Yes","No")) -> Yes | X16: urgent award - DD to follow
A17: CF-2025-021 | B17: Oakfield Carers Network | C17: 1166666 | D17: Community Fund | E17: Sarah J | F17: 20000 | G17: =SUMIFS(Payments!$D:$D,Payments!$A:$A,$A17,Payments!$I:$I,"<>") -> 20000 | H17: 45931 | I17: 46295 | J17: yes | K17: 45925 | N17: 46113 | O17: 46113 | P17: 46326 | R17: received with interim | S17: Received | T17: =IF($A17="","",IF(AND(N17<>"",O17="",N17<TODAY()),"Interim overdue "&(TODAY()-N17)&"d",IF(AND(P17<>"",Q17="",P17<TODAY()),"Final overdue "&(TODAY()-P17)&"d",IF(AND(N17<>"",O17="",N17-TODAY()<=30),"Interim due in "&(N17-TODAY())&"d",IF(AND(P17<>"",Q17="",P17-TODAY()<=30),"Final due in "&(P17-TODAY())&"d","OK"))))) -> OK | U17: =IF($A17="","",IF(COUNTIFS(Payments!$A:$A,$A17,Payments!$J:$J,"Blocked*")>0,"Payment blocked",IF(COUNTIFS(Payments!$A:$A,$A17,Payments!$J:$J,"Ready*")>0,"Payment ready",""))) | V17: =IF($A17="","",IF(K17="","No DD date; ",IF(ISNUMBER(K17),IF(TODAY()-K17>365,"DD over 12 months; ",""),"DD date unknown; "))&IF(J17="","No agreement; ","")&IF(M17="No","Condition open; ","")&IF(OR(S17="Missing",S17="Partial"),"Evidence "&LOWER(S17)&"; ","")) -> DD over 12 months; | W17: =IF($A17="","",IF(OR(T17<>"OK",U17<>"",V17<>""),"Yes","No")) -> Yes
A18: CF-2025-022 | B18: Northbridge Men's Shed | C18: 1160000 | D18: Community Fund | E18: Tom B | F18: 6000 | G18: =SUMIFS(Payments!$D:$D,Payments!$A:$A,$A18,Payments!$I:$I,"<>") -> 6000 | H18: 45931 | I18: 46295 | J18: yes | K18: 45920 | P18: 46326 | T18: =IF($A18="","",IF(AND(N18<>"",O18="",N18<TODAY()),"Interim overdue "&(TODAY()-N18)&"d",IF(AND(P18<>"",Q18="",P18<TODAY()),"Final overdue "&(TODAY()-P18)&"d",IF(AND(N18<>"",O18="",N18-TODAY()<=30),"Interim due in "&(N18-TODAY())&"d",IF(AND(P18<>"",Q18="",P18-TODAY()<=30),"Final due in "&(P18-TODAY())&"d","OK"))))) -> OK | U18: =IF($A18="","",IF(COUNTIFS(Payments!$A:$A,$A18,Payments!$J:$J,"Blocked*")>0,"Payment blocked",IF(COUNTIFS(Payments!$A:$A,$A18,Payments!$J:$J,"Ready*")>0,"Payment ready",""))) | V18: =IF($A18="","",IF(K18="","No DD date; ",IF(ISNUMBER(K18),IF(TODAY()-K18>365,"DD over 12 months; ",""),"DD date unknown; "))&IF(J18="","No agreement; ","")&IF(M18="No","Condition open; ","")&IF(OR(S18="Missing",S18="Partial"),"Evidence "&LOWER(S18)&"; ","")) -> DD over 12 months; | W18: =IF($A18="","",IF(OR(T18<>"OK",U18<>"",V18<>""),"Yes","No")) -> Yes
A19: YM25/09 | B19: Rhythm & Roots Drumming | D19: Youth Music | E19: Tom B | F19: 7200 | G19: =SUMIFS(Payments!$D:$D,Payments!$A:$A,$A19,Payments!$I:$I,"<>") -> 3600 | H19: 45940 | I19: 46304 | J19: yes | K19: 45935 | N19: 46122 | P19: 46335 | T19: =IF($A19="","",IF(AND(N19<>"",O19="",N19<TODAY()),"Interim overdue "&(TODAY()-N19)&"d",IF(AND(P19<>"",Q19="",P19<TODAY()),"Final overdue "&(TODAY()-P19)&"d",IF(AND(N19<>"",O19="",N19-TODAY()<=30),"Interim due in "&(N19-TODAY())&"d",IF(AND(P19<>"",Q19="",P19-TODAY()<=30),"Final due in "&(P19-TODAY())&"d","OK"))))) -> Interim overdue 171d | U19: =IF($A19="","",IF(COUNTIFS(Payments!$A:$A,$A19,Payments!$J:$J,"Blocked*")>0,"Payment blocked",IF(COUNTIFS(Payments!$A:$A,$A19,Payments!$J:$J,"Ready*")>0,"Payment ready",""))) -> Payment blocked | V19: =IF($A19="","",IF(K19="","No DD date; ",IF(ISNUMBER(K19),IF(TODAY()-K19>365,"DD over 12 months; ",""),"DD date unknown; "))&IF(J19="","No agreement; ","")&IF(M19="No","Condition open; ","")&IF(OR(S19="Missing",S19="Partial"),"Evidence "&LOWER(S19)&"; ","")) | W19: =IF($A19="","",IF(OR(T19<>"OK",U19<>"",V19<>""),"Yes","No")) -> Yes | X19: project paused - lead worker on leave; extension agreed?? no record
A20: CAP-10 | B20: Eastfield Village Hall | C20: 1123456 | D20: Capital Grants | E20: Priya K | F20: 3500 | G20: =SUMIFS(Payments!$D:$D,Payments!$A:$A,$A20,Payments!$I:$I,"<>") -> 0 | H20: 46249 | I20: 46477 | J20: yes | K20: 46071 | P20: 46477 | R20: quote for ramp received 02/09/2026 | S20: Received | T20: =IF($A20="","",IF(AND(N20<>"",O20="",N20<TODAY()),"Interim overdue "&(TODAY()-N20)&"d",IF(AND(P20<>"",Q20="",P20<TODAY()),"Final overdue "&(TODAY()-P20)&"d",IF(AND(N20<>"",O20="",N20-TODAY()<=30),"Interim due in "&(N20-TODAY())&"d",IF(AND(P20<>"",Q20="",P20-TODAY()<=30),"Final due in "&(P20-TODAY())&"d","OK"))))) -> OK | U20: =IF($A20="","",IF(COUNTIFS(Payments!$A:$A,$A20,Payments!$J:$J,"Blocked*")>0,"Payment blocked",IF(COUNTIFS(Payments!$A:$A,$A20,Payments!$J:$J,"Ready*")>0,"Payment ready",""))) -> Payment blocked | V20: =IF($A20="","",IF(K20="","No DD date; ",IF(ISNUMBER(K20),IF(TODAY()-K20>365,"DD over 12 months; ",""),"DD date unknown; "))&IF(J20="","No agreement; ","")&IF(M20="No","Condition open; ","")&IF(OR(S20="Missing",S20="Partial"),"Evidence "&LOWER(S20)&"; ","")) | W20: =IF($A20="","",IF(OR(T20<>"OK",U20<>"",V20<>""),"Yes","No")) -> Yes

Sheet Data questions
A1: Row in your file | B1: Grant ref | C1: Recipient | D1: Field | E1: Value in your file | F1: Question | G1: What I assumed | H1: Your answer
A2: 3 | B2: CF-2025-009 | C2: Harbour Youth Proj. | D2: dd_checked | E2: Y | F2: Due diligence ticked but no date recorded. When was it done? | G2: Treated as done, date unknown
A3: 5 | B3: YM25/05 | C3: St Anne's Community Choir | D3: notes | E3: paid before agreement returned?? check | F3: Note needs a decision or confirmation.
A4: 6 | B4: CAP-7 | C4: Riverside Scout Group | D4: award_date | E4: Jan-26 | F4: Award date: month only ('Jan-26'); assumed 1st of month. | G4: Used as stated
A5: 7 | B5: CAP-8 | C5: Eastfield Village Hall | D5: evidence | E5: completion certificate + photos | F5: Evidence named but status unclear: received or still missing?
A6: 7 | B6: CAP-8 | C6: Eastfield Village Hall | D6: notes | E6: bank details changed - verify before next payment! | F6: Note needs a decision or confirmation.
A7: 9 | B7: HF-102 | C7: Mercy St Foodbank | D7: agreement_signed | E7: pending | F7: Agreement not yet signed? | G7: Treated as not signed
A8: 11 | B8: CF-2026-005 | C8: Greenway Allotment Society | D8: evidence | E8: photos of new raised beds | F8: Evidence named but status unclear: received or still missing?
A9: 11 | B9: CF-2026-005 | C9: Greenway Allotment Society | D9: owner | F9: No owner recorded. Who is responsible for this grant?
A10: 14 | B10: YM26/02 | C10: The Beat Box Studio CIC | D10: reg_no | E10: CIC 12345678 | F10: Registration number is not a standard charity number. Is this a company/CIC number? | G10: Kept as given
A11: 19 | B11: YM25/09 | C11: Rhythm & Roots Drumming | D11: notes | E11: project paused - lead worker on leave; extension agreed?? no record | F11: Note needs a decision or confirmation.
A12: 20 | C12: Friends of Castle Park | D12: grant_ref | F12: No grant reference, dates or agreement: awarded but not yet set up? | G12: Listed as a set-up action, not as an active grant
A13: 8 | B13: HF-101 | C13: Mercy Street Food Bank | D13: recipient | E13: Mercy St Foodbank / Mercy Street Food Bank | F13: Same organisation spelt differently? | G13: Treated as one organisation
A14: 2 | B14: CF-2025-014 | C14: Harbour Youth Project CIO | D14: recipient | E14: Harbour Youth Proj. / Harbour Youth Project CIO | F14: Same organisation under two names? | G14: Kept separate until confirmed
D15: owner | E15: Priya, Priya K | F15: Owner written several ways. Same owner? | G15: Grouped as 'Priya K'
D16: owner | E16: Sarah, sarah j, Sarah J, SJ | F16: Owner written several ways. Same owner? | G16: Grouped as 'Sarah J'
D17: owner | E17: TB, Tom, Tom B | F17: Owner written several ways. Same owner? | G17: Grouped as 'Tom B'
D18: fund | E18: Capital, Capital Grants | F18: Fund written several ways. Same fund? | G18: Grouped as 'Capital Grants'
D19: fund | E19: Community Fund, community fund | F19: Fund written several ways. Same fund? | G19: Grouped as 'Community Fund'
D20: fund | E20: Hardship, Hardship Fund | F20: Fund written several ways. Same fund? | G20: Grouped as 'Hardship Fund'
A21: 6 | B21: CAP-7 | C21: Riverside Scout Group | D21: payment_schedule | E21: 3 x quarterly; £20,000 paid | F21: Schedule says 3 quarterly payments and £20,000 is paid. I have assumed two £10,000 payments made and the third (£20,000) due 1 Oct once planning permission evidence is in. Are those the right amounts? | G21: Assumed exactly that
A22: 13 | B22: YM26/01 | C22: Brass for All | D22: payment_schedule | E22: Feb after termly report | F22: The February payment depends on the spring termly report, which has no column in your sheet. I have recorded it as a condition dated 15 Jan 2027. OK? | G22: Tracked as a condition
D23: paid dates | E23: paid to date only | F23: Your sheet records how much has been paid but not when. Paid tranches show 'yes' instead of a date; add dates if you want them in the audit trail. | G23: Paid = yes, date unknown
A24: 9 | B24: HF-102 | C24: Mercy St Foodbank | D24: recipient | E24: same charity no. 1170777 | F24: HF-101 and HF-102 share charity number 1170777, so I have used one name for both. | G24: Named Mercy Street Food Bank

Sheet How to use
A1: How to keep this workbook working
A3: 1. Record events as they happen: enter the date a report arrives (Grant register, 'received' columns), set Evidence status, set 'Conditions met?', and enter the date each tranche is paid (Payments, 'Paid (date)').
A5: 2. The Report status, Payments, Checks and Status columns recalculate from those dates every day. Filter 'Needs attention?' = Yes on the Grant register to see what still needs action.
A7: 3. Each tranche has a 'Released when' condition. Status shows 'Ready for approval' once that condition is met and the payment is within 30 days, and 'Blocked' if the payment is due but the condition is not met.
A9: 4. If a grantee reports new bank details, set 'Bank details check' to Verify until you have confirmed the change by phone on a number you already hold. The tranche stays blocked until you set it back to OK.
A11: 5. 'Needs attention' is the list as at the build date. Tick Done as items are cleared. Within 60 days of delivery I will refresh it once from an updated export at no extra cost.
A13: 6. This workbook organises information you supplied. It does not move money, contact grantees or give legal, audit or regulatory advice; decisions stay with you and your trustees.
